Workbook

Sheet Profit and Loss
B2: Demo Café Group
B3: Profit and loss (KSh '000)
B4: Account / breakdown | F4: 2024 | G4: 2025 | H4: Variance | I4: Variance % | J4: Remarks
B5: Revenue | F5: =ROUND(SUM('Profit and Loss'!F6,'Profit and Loss'!F7,'Profit and Loss'!F8),0) -> 4053112 | G5: =ROUND(SUM('Profit and Loss'!G6,'Profit and Loss'!G7,'Profit and Loss'!G8),0) -> 4345651 | H5: =G5-F5 -> 292539 | I5: =IF(F5=0,"",H5/ABS(F5)) -> 0.072176392 | J5: Revenue increased by KSh 292.539m (7.2%) compared with 2024. Beverage sales contributed KSh 208.683m of the KSh 292.539m growth, while food-related sales added KSh 78.671m. The wider outlet network and a strong December trading period supported the increase.
B6: Revenue from sale of food | F6: 2750555.5 | G6: 2829227 | H6: =G6-F6 -> 78671.489 | I6: =IF(F6=0,"",H6/ABS(F6)) -> 0.028602037 | J6: Revenue from sale of food increased by KSh 78.671m (2.9%) compared with 2024. The increase is consistent with a larger trading network, although growth was modest relative to total revenue. Food-related sales therefore contributed less to overall growth than beverages.
B7: Revenue from sale of beverages | F7: 1294302.5 | G7: 1502985.3 | H7: =G7-F7 -> 208682.8 | I7: =IF(F7=0,"",H7/ABS(F7)) -> 0.16123187 | J7: Revenue from sale of beverages increased by KSh 208.683m (16.1%) compared with 2024. This was the main revenue growth driver, contributing about 71% of the total increase. The movement is consistent with higher beverage volumes across the expanded restaurant network.
B8: Revenue from sale of other items | F8: 8253.751 | G8: 13438.51 | H8: =G8-F8 -> 5184.759 | I8: =IF(F8=0,"",H8/ABS(F8)) -> 0.62817003 | J8: Revenue from sale of other items increased by KSh 5.185m (62.8%) compared with 2024. The increase came from a small base and includes tobacco and other ancillary sales. Reclassification between food, beverage and other revenue categories may also affect the year-on-year comparison.
B10: Cost of sales | F10: =-ROUND('Schedule of Expenses'!F11,0) -> -2026099 | G10: =-ROUND('Schedule of Expenses'!G11,0) -> -2067896 | H10: =G10-F10 -> -41797 | I10: =IF(F10=0,"",H10/ABS(F10)) -> -0.020629298 | J10: Cost of sales increased by KSh 41.797m (2.1%) compared with 2024. Food costs and production salaries increased by KSh 35.941m and KSh 21.155m respectively. These increases were partly offset by lower utilities, packaging and kitchen-equipment depreciation.
B11: Food costs | F11: =-'Schedule of Expenses'!F6 -> -1460153.8 | G11: =-'Schedule of Expenses'!G6 -> -1496095.2 | H11: =G11-F11 -> -35941.318 | I11: =IF(F11=0,"",H11/ABS(F11)) -> -0.024614748 | J11: Food costs increased by KSh 35.941m (2.5%) compared with 2024. The movement reflects higher consumption as sales and the outlet network expanded. Costs grew more slowly than revenue, improving food-cost absorption during the year.
B12: Lighting, water and heating | F12: =-'Schedule of Expenses'!F7 -> -233482.13 | G12: =-'Schedule of Expenses'!G7 -> -226081.31 | H12: =G12-F12 -> 7400.82 | I12: =IF(F12=0,"",H12/ABS(F12)) -> 0.031697586 | J12: Lighting, water and heating decreased by KSh 7.401m (3.2%) compared with 2024. Utility costs reduced despite higher sales, indicating improved consumption or tariff management. The cost represented a lower proportion of revenue than in 2024.
B13: Depreciation - kitchen equipment | F13: =-'Schedule of Expenses'!F8 -> -45877.086 | G13: =-'Schedule of Expenses'!G8 -> -43082.723 | H13: =G13-F13 -> 2794.363 | I13: =IF(F13=0,"",H13/ABS(F13)) -> 0.060909775 | J13: Depreciation - kitchen equipment decreased by KSh 2.794m (6.1%) compared with 2024. The lower charge is consistent with disposals and the changing age profile of kitchen assets. Current-year additions partly offset the reduction in the depreciable base.
B14: Packaging materials | F14: =-'Schedule of Expenses'!F9 -> -83870.664 | G14: =-'Schedule of Expenses'!G9 -> -78766.514 | H14: =G14-F14 -> 5104.15 | I14: =IF(F14=0,"",H14/ABS(F14)) -> 0.060857393 | J14: Packaging materials decreased by KSh 5.104m (6.1%) compared with 2024. Packaging costs fell despite revenue growth, suggesting better purchasing, stock control or lower packaging intensity. This provided a favourable offset within cost of sales.
B15: Salaries | F15: =-'Schedule of Expenses'!F10 -> -202715.31 | G15: =-'Schedule of Expenses'!G10 -> -223870.54 | H15: =G15-F15 -> -21155.221 | I15: =IF(F15=0,"",H15/ABS(F15)) -> -0.10435926 | J15: Salaries increased by KSh 21.155m (10.4%) compared with 2024. Production payroll rose as the business operated a broader outlet network. The increase was above food-sales growth, indicating a higher staffing run rate during the year.
B16: Gross profit | F16: =SUM('Profit and Loss'!F5,'Profit and Loss'!F10) -> 2027013 | G16: =SUM('Profit and Loss'!G5,'Profit and Loss'!G10) -> 2277755 | H16: =G16-F16 -> 250742 | I16: =IF(F16=0,"",H16/ABS(F16)) -> 0.12370024 | J16: Gross profit increased by KSh 250.742m (12.4%) compared with 2024. Revenue grew by KSh 292.539m while cost of sales increased by only KSh 41.797m. As a result, gross margin improved from about 50.0% to 52.4%.
B18: Other operating income | F18: =SUM('Profit and Loss'!F19,'Profit and Loss'!F20) -> 4815.158 | G18: =SUM('Profit and Loss'!G19,'Profit and Loss'!G20) -> 1411.782 | H18: =G18-F18 -> -3403.376 | I18: =IF(F18=0,"",H18/ABS(F18)) -> -0.70680464 | J18: Other operating income decreased by KSh 3.403m (70.7%) compared with 2024. The reduction mainly reflects the non-recurrence of KSh 3.554m of other income reported in 2024. The increase in interest income was not sufficient to offset this fall.
B19: Interest income | F19: 1260.674 | G19: 1411.782 | H19: =G19-F19 -> 151.108 | I19: =IF(F19=0,"",H19/ABS(F19)) -> 0.11986287 | J19: Interest income increased by KSh 0.151m (12.0%) compared with 2024. The increase is consistent with higher returns on staff loans and foreign-currency project balances. The movement was modest in absolute terms and did not materially affect operating results.
B20: Other income | F20: 3554.484 | G20: 0 | H20: =G20-F20 -> -3554.484 | I20: =IF(F20=0,"",H20/ABS(F20)) -> -1 | J20: Other income was nil in 2025, compared with KSh 3.554m in 2024. The separate miscellaneous-income balance reported in 2024 did not recur in 2025. This appears to reflect a change in classification or the absence of the underlying one-off income.
B22: Sales and marketing expenses | F22: =-ROUND('Schedule of Expenses'!F16,0) -> -115182 | G22: =-ROUND('Schedule of Expenses'!G16,0) -> -154247 | H22: =G22-F22 -> -39065 | I22: =IF(F22=0,"",H22/ABS(F22)) -> -0.3391589 | J22: Sales and marketing expenses increased by KSh 39.065m (33.9%) compared with 2024. Advertising and delivery costs increased by KSh 26.196m and KSh 12.869m respectively. The higher spend is consistent with expanded marketing activity and growth in delivery-based sales.
B23: Advertising costs | F23: =-'Schedule of Expenses'!F14 -> -55650.826 | G23: =-'Schedule of Expenses'!G14 -> -81846.882 | H23: =G23-F23 -> -26196.056 | I23: =IF(F23=0,"",H23/ABS(F23)) -> -0.47072178 | J23: Advertising costs increased by KSh 26.196m (47.1%) compared with 2024. The increase reflects heavier campaign activity, including outlet launches, airport-location marketing, consultancy support and billboards. The scale of growth was well above revenue growth and should be supported by campaign documentation.
B24: Delivery costs | F24: =-'Schedule of Expenses'!F15 -> -59531.207 | G24: =-'Schedule of Expenses'!G15 -> -72400.102 | H24: =G24-F24 -> -12868.895 | I24: =IF(F24=0,"",H24/ABS(F24)) -> -0.21617057 | J24: Delivery costs increased by KSh 12.869m (21.6%) compared with 2024. The movement is consistent with higher delivery volumes and platform commissions. Delivery charges remained concentrated among the major delivery platforms.
B26: Administrative expenses | F26: =-ROUND('Schedule of Expenses'!F53,0) -> -1000264 | G26: =-ROUND('Schedule of Expenses'!G53,0) -> -1157300 | H26: =G26-F26 -> -157036 | I26: =IF(F26=0,"",H26/ABS(F26)) -> -0.15699455 | J26: Administrative expenses increased by KSh 157.036m (15.7%) compared with 2024. Employment costs increased by KSh 90.891m and other administration costs by KSh 66.145m. Payroll, professional services, travel and directors’ remuneration were the main drivers.
B27: Employment
B28: Salaries and wages | F28: =-'Schedule of Expenses'!F20 -> -745941 | G28: =-'Schedule of Expenses'!G20 -> -798708.54 | H28: =G28-F28 -> -52767.536 | I28: =IF(F28=0,"",H28/ABS(F28)) -> -0.070739557 | J28: Salaries and wages increased by KSh 52.768m (7.1%) compared with 2024. The increase was mainly driven by the KSh 46.022m rise in salaries excluding NSSF and KSh 6.745m in employer NSSF. This is consistent with a larger workforce and higher payroll run rate across the expanded network.
B29: Salaries excluding NSSF | F29: =-'Schedule of Expenses'!F21 -> -715425.5 | G29: =-'Schedule of Expenses'!G21 -> -761447.58 | H29: =G29-F29 -> -46022.081 | I29: =IF(F29=0,"",H29/ABS(F29)) -> -0.064328265 | J29: Salaries excluding NSSF increased by KSh 46.022m (6.4%) compared with 2024. The movement reflects the higher staffing requirement of the expanded outlet network. The year-end payroll run rate was above the level recorded at the start of the year.
B30: National Social Security Fund | F30: =-'Schedule of Expenses'!F22 -> -30515.502 | G30: =-'Schedule of Expenses'!G22 -> -37260.957 | H30: =G30-F30 -> -6745.455 | I30: =IF(F30=0,"",H30/ABS(F30)) -> -0.22105011 | J30: National Social Security Fund increased by KSh 6.745m (22.1%) compared with 2024. Employer contributions rose faster than base salaries, consistent with statutory contribution changes and a larger covered payroll. The contribution should be agreed to payroll and statutory returns.
B31: Staff welfare | F31: =-'Schedule of Expenses'!F23 -> -9231.594 | G31: =-'Schedule of Expenses'!G23 -> -9970.814 | H31: =G31-F31 -> -739.22 | I31: =IF(F31=0,"",H31/ABS(F31)) -> -0.080075012 | J31: Staff welfare increased by KSh 0.739m (8.0%) compared with 2024. The increase is consistent with higher welfare and training needs for a larger workforce. The movement remained modest relative to total employment costs.
B32: Staff uniform | F32: =-'Schedule of Expenses'!F24 -> -4975.708 | G32: =-'Schedule of Expenses'!G24 -> -5053.69 | H32: =G32-F32 -> -77.982 | I32: =IF(F32=0,"",H32/ABS(F32)) -> -0.015672543 | J32: Staff uniform increased by KSh 0.078m (1.6%) compared with 2024. Uniform expenditure was broadly stable despite the wider outlet network. This suggests purchases were controlled or uniforms issued in prior periods continued to be used.
B33: Staff transport | F33: =-'Schedule of Expenses'!F25 -> -42533.02 | G33: =-'Schedule of Expenses'!G25 -> -45581.238 | H33: =G33-F33 -> -3048.218 | I33: =IF(F33=0,"",H33/ABS(F33)) -> -0.071667095 | J33: Staff transport increased by KSh 3.048m (7.2%) compared with 2024. The increase is consistent with additional staff and locations requiring transport support. Growth was broadly in line with revenue.
B34: Work permit expenses | F34: =-'Schedule of Expenses'!F26 -> -940.016 | G34: =-'Schedule of Expenses'!G26 -> -4685.898 | H34: =G34-F34 -> -3745.882 | I34: =IF(F34=0,"",H34/ABS(F34)) -> -3.984913 | J34: Work permit expenses increased by KSh 3.746m (398.5%) compared with 2024. The sharp increase reflects several significant permit-related payments during the year. The movement is concentrated and should be supported by the relevant permits and payment records.
B35: Net change in provision for leave | F35: =-'Schedule of Expenses'!F27 -> 19101.286 | G35: =-'Schedule of Expenses'!G27 -> -480.034 | H35: =G35-F35 -> -19581.32 | I35: =IF(F35=0,"",H35/ABS(F35)) -> -1.025131 | J35: Net change in provision for leave moved from a credit of KSh 19.101m in 2024 to a charge of KSh 0.480m in 2025. The prior-year leave-provision reversal did not recur. A small charge was recognised in 2025, creating an adverse year-on-year movement of KSh 19.581m.
B36: Provision for gratuity | F36: =-'Schedule of Expenses'!F28 -> -4340.52 | G36: =-'Schedule of Expenses'!G28 -> -5249.309 | H36: =G36-F36 -> -908.789 | I36: =IF(F36=0,"",H36/ABS(F36)) -> -0.2093733 | J36: Provision for gratuity increased by KSh 0.909m (20.9%) compared with 2024. The higher charge is consistent with an increased employee-benefit obligation and service cost. The final expense should agree to the actuarial report and gratuity reconciliation.
B37: Gratuity interest cost | F37: =-'Schedule of Expenses'!F29 -> 0 | G37: =-'Schedule of Expenses'!G29 -> -10022.322 | H37: =G37-F37 -> -10022.322 | I37: =IF(F37=0,"",H37/ABS(F37)) | J37: Gratuity interest cost was recorded at KSh 10.022m in 2025, with no comparable amount in 2024. A separate interest cost on the gratuity obligation was recognised for the first time in 2025. This added KSh 10.022m to employment costs and should agree to the actuarial valuation.
B38: Total employment costs | F38: =-'Schedule of Expenses'!F30 -> -788860.57 | G38: =-'Schedule of Expenses'!G30 -> -879751.84 | H38: =G38-F38 -> -90891.269 | I38: =IF(F38=0,"",H38/ABS(F38)) -> -0.11521842 | J38: Total employment costs increased by KSh 90.891m (11.5%) compared with 2024. The main drivers were the KSh 52.768m rise in salaries and NSSF, the KSh 19.581m leave-provision swing and the new KSh 10.022m gratuity interest charge. Together, these explain most of the increase.
B39: Other administration expenses
B40: Directors remuneration | F40: =-'Schedule of Expenses'!F33 -> -47212.821 | G40: =-'Schedule of Expenses'!G33 -> -61535.099 | H40: =G40-F40 -> -14322.279 | I40: =IF(F40=0,"",H40/ABS(F40)) -> -0.30335571 | J40: Directors remuneration increased by KSh 14.322m (30.3%) compared with 2024. The increase forms part of the overall rise in compensation costs. The balance should be agreed to approved remuneration schedules and related-party disclosures.
B41: Directors expenses | F41: =-'Schedule of Expenses'!F34 -> -4080 | G41: =-'Schedule of Expenses'!G34 -> -7055.7 | H41: =G41-F41 -> -2975.7 | I41: =IF(F41=0,"",H41/ABS(F41)) -> -0.72933824 | J41: Directors expenses increased by KSh 2.976m (72.9%) compared with 2024. The movement includes a director-related prior-period PAYE item recorded in 2025. This makes the increase partly non-recurring rather than purely current-year operating spend.
B42: Legal and professional fees | F42: =-'Schedule of Expenses'!F35 -> -31278.778 | G42: =-'Schedule of Expenses'!G35 -> -56211.184 | H42: =G42-F42 -> -24932.406 | I42: =IF(F42=0,"",H42/ABS(F42)) -> -0.79710294 | J42: Legal and professional fees increased by KSh 24.932m (79.7%) compared with 2024. The increase is consistent with a full year of e-commerce project support, website and catalogue services, and guest-experience roles. The balance also includes tax-related professional charges.
B43: Auditors remuneration
B44: Current year | F44: =-'Schedule of Expenses'!F37 -> -3328.755 | G44: =-'Schedule of Expenses'!G37 -> -4105.914 | H44: =G44-F44 -> -777.159 | I44: =IF(F44=0,"",H44/ABS(F44)) -> -0.23346837 | J44: Current year increased by KSh 0.777m (23.3%) compared with 2024. The audit fee increased broadly in line with the revised engagement charge. The balance should agree to the signed engagement letter and supplier invoices.
B45: Postages, telephones and internet | F45: =-'Schedule of Expenses'!F38 -> -15203.122 | G45: =-'Schedule of Expenses'!G38 -> -15463.742 | H45: =G45-F45 -> -260.62 | I45: =IF(F45=0,"",H45/ABS(F45)) -> -0.017142532 | J45: Postages, telephones and internet increased by KSh 0.261m (1.7%) compared with 2024. The modest increase is consistent with servicing more operating locations. Internet costs remain the largest component of this line.
B46: Printing and stationery | F46: =-'Schedule of Expenses'!F39 -> -17635.862 | G46: =-'Schedule of Expenses'!G39 -> -16174.117 | H46: =G46-F46 -> 1461.745 | I46: =IF(F46=0,"",H46/ABS(F46)) -> 0.082884806 | J46: Printing and stationery decreased by KSh 1.462m (8.3%) compared with 2024. The decrease is consistent with improved stock control and purchasing terms. The saving was achieved despite the larger operating network.
B47: Café decoration | F47: =-'Schedule of Expenses'!F40 -> -1375.349 | G47: =-'Schedule of Expenses'!G40 -> -5004.4 | H47: =G47-F47 -> -3629.051 | I47: =IF(F47=0,"",H47/ABS(F47)) -> -2.6386401 | J47: Café decoration increased by KSh 3.629m (263.9%) compared with 2024. The increase is consistent with decorating newly opened or refurbished outlets. The balance may also include timing effects from accruals and reversals around project completion.
B48: Motor vehicle running expenses | F48: =-'Schedule of Expenses'!F41 -> -22056.853 | G48: =-'Schedule of Expenses'!G41 -> -19606.944 | H48: =G48-F48 -> 2449.909 | I48: =IF(F48=0,"",H48/ABS(F48)) -> 0.11107246 | J48: Motor vehicle running expenses decreased by KSh 2.450m (11.1%) compared with 2024. The reduction is consistent with lower use of company vehicles after more logistics activity was outsourced. This saving was partly offset by higher travel and transport costs.
B49: Travelling and transport | F49: =-'Schedule of Expenses'!F42 -> -30178.226 | G49: =-'Schedule of Expenses'!G42 -> -46434.916 | H49: =G49-F49 -> -16256.69 | I49: =IF(F49=0,"",H49/ABS(F49)) -> -0.53868938 | J49: Travelling and transport increased by KSh 16.257m (53.9%) compared with 2024. The increase reflects the broader outlet network and greater use of outsourced logistics. Logistics-related charges appear to be the main component of the movement.
B50: Entertainment expenses | F50: =-'Schedule of Expenses'!F43 -> 737.971 | G50: =-'Schedule of Expenses'!G43 -> 0 | H50: =G50-F50 -> -737.971 | I50: =IF(F50=0,"",H50/ABS(F50)) -> -1 | J50: Entertainment expenses was nil in 2025, compared with KSh 0.738m in 2024. The prior-year balance did not recur, indicating that 2025 activities were either supplier-supported or offset by recoveries. The nil balance should be checked against the underlying gross entries.
B51: Bad debts / recoveries | F51: =-'Schedule of Expenses'!F44 -> -11.941 | G51: =-'Schedule of Expenses'!G44 -> -34.481 | H51: =G51-F51 -> -22.54 | I51: =IF(F51=0,"",H51/ABS(F51)) -> -1.8876141 | J51: Bad debts / recoveries increased by KSh 0.023m (188.8%) compared with 2024. More receivable balances were written off in 2025, although the amount remains immaterial. The write-offs should be matched to approved customer account closures.
B52: Cash sale shortages / surpluses | F52: =-'Schedule of Expenses'!F45 -> 804.758 | G52: =-'Schedule of Expenses'!G45 -> -256.535 | H52: =G52-F52 -> -1061.293 | I52: =IF(F52=0,"",H52/ABS(F52)) -> -1.3187728 | J52: Cash sale shortages / surpluses moved from a credit of KSh 0.805m in 2024 to a charge of KSh 0.257m in 2025. The prior-year net surplus changed to a net shortage in 2025. This indicates a deterioration in till or cash reconciliation outcomes and warrants review by outlet.
B53: Expected credit loss provision / reversal | F53: =-'Schedule of Expenses'!F46 -> 1947.275 | G53: =-'Schedule of Expenses'!G46 -> -3617.778 | H53: =G53-F53 -> -5565.053 | I53: =IF(F53=0,"",H53/ABS(F53)) -> -2.857867 | J53: Expected credit loss provision / reversal moved from a credit of KSh 1.947m in 2024 to a charge of KSh 3.618m in 2025. The movement from a reversal to a charge is consistent with the 43.2% increase in trade receivables. The provision should agree to the year-end ageing and expected-credit-loss model.
B54: Bank charges and commissions | F54: =-'Schedule of Expenses'!F47 -> -43925.823 | G54: =-'Schedule of Expenses'!G47 -> -44938.634 | H54: =G54-F54 -> -1012.811 | I54: =IF(F54=0,"",H54/ABS(F54)) -> -0.023057303 | J54: Bank charges and commissions increased by KSh 1.013m (2.3%) compared with 2024. The increase is consistent with higher card and mobile-money transaction volumes as sales grew. Charges rose more slowly than revenue, indicating improved processing-cost absorption.
B55: Penalties | F55: =-'Schedule of Expenses'!F48 -> -681.689 | G55: =-'Schedule of Expenses'!G48 -> 0 | H55: =G55-F55 -> 681.689 | I55: =IF(F55=0,"",H55/ABS(F55)) -> 1 | J55: Penalties was nil in 2025, compared with KSh 0.682m in 2024. No operating penalties were recorded in 2025, removing the prior-year charge. Any finance-related penalties are presented separately within finance costs.
... B59: Total other administrative expenses | F59: =-'Schedule of Expenses'!F52 -> -211403.18 | G59: =-'Schedule of Expenses'!G52 -> -277547.85 | H59: =G59-F59 -> -66144.668 | I59: =IF(F59=0,"",H59/ABS(F59)) -> -0.31288397 | J59: Total other administrative expenses increased by KSh 66.145m (31.3%) compared with 2024. Professional fees, travel and directors’ remuneration were the largest increases. These were partly offset by lower motor-vehicle, printing and stationery costs and higher realised exchange gains.
B61: Other operating expenses | F61: =-ROUND('Schedule of Expenses'!F70,0) -> -756471 | G61: =-ROUND('Schedule of Expenses'!G70,0) -> -727746 | H61: =G61-F61 -> 28725 | I61: =IF(F61=0,"",H61/ABS(F61)) -> 0.037972374 | J61: Other operating expenses decreased by KSh 28.725m (3.8%) compared with 2024. The larger gain on lease termination and the non-recurrence of trademark impairment reduced net costs. These benefits outweighed the adverse disposal movement and higher rent, repairs and security costs.
B62: Commercial rent | F62: =-'Schedule of Expenses'!F56 -> -151640.2 | G62: =-'Schedule of Expenses'!G56 -> -162816.41 | H62: =G62-F62 -> -11176.217 | I62: =IF(F62=0,"",H62/ABS(F62)) -> -0.073702206 | J62: Commercial rent increased by KSh 11.176m (7.4%) compared with 2024. The increase is consistent with additional operating locations and higher turnover-based rentals. Lower rent-concession credits also increased the net rental burden.
B63: Discount on rent concessions | F63: =-'Schedule of Expenses'!F57 -> 33153.248 | G63: =-'Schedule of Expenses'!G57 -> 29575.948 | H63: =G63-F63 -> -3577.3 | I63: =IF(F63=0,"",H63/ABS(F63)) -> -0.10790195 | J63: Discount on rent concessions decreased by KSh 3.577m (10.8%) compared with 2024. Rent-concession credits reduced in 2025, providing less relief against gross rental expense. This contributed to the increase in net occupancy costs.
B64: Repairs and maintenance | F64: =-'Schedule of Expenses'!F58 -> -75611.803 | G64: =-'Schedule of Expenses'!G58 -> -90080.999 | H64: =G64-F64 -> -14469.196 | I64: =IF(F64=0,"",H64/ABS(F64)) -> -0.19136161 | J64: Repairs and maintenance increased by KSh 14.469m (19.1%) compared with 2024. The increase is consistent with maintaining a larger and ageing outlet network. The balance includes both recurring maintenance contracts and ad hoc repairs.
B65: Licences | F65: =-'Schedule of Expenses'!F59 -> -20231.739 | G65: =-'Schedule of Expenses'!G59 -> -19863.963 | H65: =G65-F65 -> 367.776 | I65: =IF(F65=0,"",H65/ABS(F65)) -> 0.01817817 | J65: Licences decreased by KSh 0.368m (1.8%) compared with 2024. The slight reduction suggests lower effluent or other licence charges, partly offsetting the effect of additional locations. The account was broadly stable year on year.
B66: Lighting, water and heating | F66: =-'Schedule of Expenses'!F60 -> 0 | G66: =-'Schedule of Expenses'!G60 -> 0 | H66: =G66-F66 -> 0 | I66: =IF(F66=0,"",H66/ABS(F66)) | J66: No balance was recorded for lighting, water and heating in either year. Utility costs reduced despite higher sales, indicating improved consumption or tariff management. The cost represented a lower proportion of revenue than in 2024.
B67: Insurance expenses | F67: =-'Schedule of Expenses'!F61 -> -26136.311 | G67: =-'Schedule of Expenses'!G61 -> -27715.086 | H67: =G67-F67 -> -1578.775 | I67: =IF(F67=0,"",H67/ABS(F67)) -> -0.060405426 | J67: Insurance expenses increased by KSh 1.579m (6.0%) compared with 2024. The increase is consistent with insuring additional outlets and assets. Growth remained below the expansion in the right-of-use asset base.
B68: Security | F68: =-'Schedule of Expenses'!F62 -> -9697.866 | G68: =-'Schedule of Expenses'!G62 -> -12335.186 | H68: =G68-F68 -> -2637.32 | I68: =IF(F68=0,"",H68/ABS(F68)) -> -0.27194849 | J68: Security increased by KSh 2.637m (27.2%) compared with 2024. The movement reflects security services for additional locations. The increase was significant relative to revenue and should be supported by contracts and outlet listings.
B69: Cleaning expenses | F69: =-'Schedule of Expenses'!F63 -> -42557.113 | G69: =-'Schedule of Expenses'!G63 -> -43723.412 | H69: =G69-F69 -> -1166.299 | I69: =IF(F69=0,"",H69/ABS(F69)) -> -0.027405501 | J69: Cleaning expenses increased by KSh 1.166m (2.7%) compared with 2024. Cleaning costs increased only modestly despite the wider outlet network. This indicates relatively stable unit costs or efficiencies in service arrangements.
B70: Loss / gain on disposal of property and equipment | F70: =-'Schedule of Expenses'!F64 -> 47584.405 | G70: =-'Schedule of Expenses'!G64 -> -11198.99 | H70: =G70-F70 -> -58783.395 | I70: =IF(F70=0,"",H70/ABS(F70)) -> -1.23535 | J70: Loss / gain on disposal of property and equipment moved from a credit of KSh 47.584m in 2024 to a charge of KSh 11.199m in 2025. A disposal gain in 2024 changed to a loss in 2025, producing a KSh 58.783m adverse swing. The movement should agree to the fixed-asset disposal schedule and sale proceeds.
B71: Gain on lease termination | F71: =-'Schedule of Expenses'!F65 -> 6604.337 | G71: =-'Schedule of Expenses'!G65 -> 91196.041 | H71: =G71-F71 -> 84591.704 | I71: =IF(F71=0,"",H71/ABS(F71)) -> 12.808508 | J71: Gain on lease termination increased by KSh 84.592m (1,280.9%) compared with 2024. The larger gain reflects lease terminations or modifications where liabilities released exceeded the related right-of-use assets removed. The balance should agree to the lease modification calculations.
B72: Impairment of acquired trademarks | F72: =-'Schedule of Expenses'!F66 -> -18500 | G72: =-'Schedule of Expenses'!G66 -> 0 | H72: =G72-F72 -> 18500 | I72: =IF(F72=0,"",H72/ABS(F72)) -> 1 | J72: Impairment of acquired trademarks was nil in 2025, compared with KSh 18.500m in 2024. The trademarks were fully impaired in 2024, so no further charge arose in 2025. The nil closing carrying value explains the non-recurrence.
B73: Amortisation of intangible assets | F73: =-'Schedule of Expenses'!F67 -> -1829.13 | G73: =-'Schedule of Expenses'!G67 -> -6184.929 | H73: =G73-F73 -> -4355.799 | I73: =IF(F73=0,"",H73/ABS(F73)) -> -2.3813502 | J73: Amortisation of intangible assets increased by KSh 4.356m (238.1%) compared with 2024. The increase is consistent with additions to software and other intangible assets during the year. The charge should agree to the intangible-asset register and useful lives applied.
... B75: Depreciation of property, plant and equipment | F75: =-'Schedule of Expenses'!F69 -> -191550.54 | G75: =-'Schedule of Expenses'!G69 -> -176972.42 | H75: =G75-F75 -> 14578.116 | I75: =IF(F75=0,"",H75/ABS(F75)) -> 0.076105849 | J75: Depreciation of property, plant and equipment decreased by KSh 14.578m (7.6%) compared with 2024. The lower charge is consistent with disposals and fully depreciated assets, partly offset by current-year additions. The movement should agree to the fixed-asset register.
B76: Operating profit | F76: =SUM('Profit and Loss'!F16,'Profit and Loss'!F18,'Profit and Loss'!F22,'Profit and Loss'!F26,'Profit and Loss'!F61) -> 159911.16 | G76: =SUM('Profit and Loss'!G16,'Profit and Loss'!G18,'Profit and Loss'!G22,'Profit and Loss'!G26,'Profit and Loss'!G61) -> 239873.78 | H76: =G76-F76 -> 79962.624 | I76: =IF(F76=0,"",H76/ABS(F76)) -> 0.50004406 | J76: Operating profit increased by KSh 79.963m (50.0%) compared with 2024. Gross profit improved by KSh 250.742m and other operating expenses reduced by KSh 28.725m. These gains more than offset higher administration and marketing costs, resulting in a KSh 79.963m increase.
B78: Finance costs | F78: =ROUND(SUM('Profit and Loss'!F79,'Profit and Loss'!F80,'Profit and Loss'!F81,'Profit and Loss'!F82,'Profit and Loss'!F83,'Profit and Loss'!F84,'Profit and Loss'!F85),0) -> -277003 | G78: =ROUND(SUM('Profit and Loss'!G79,'Profit and Loss'!G80,'Profit and Loss'!G81,'Profit and Loss'!G82,'Profit and Loss'!G83,'Profit and Loss'!G84,'Profit and Loss'!G85),0) -> -287965 | H78: =G78-F78 -> -10962 | I78: =IF(F78=0,"",H78/ABS(F78)) -> -0.039573579 | J78: Finance costs increased by KSh 10.962m (4.0%) compared with 2024. Lower overdraft and loan interest saved KSh 54.617m, but realised and unrealised exchange gains reduced by KSh 62.593m. Higher lease interest also contributed to the net increase.
B79: Bank overdraft interest | F79: -47503.97 | G79: -21456.918 | H79: =G79-F79 -> 26047.052 | I79: =IF(F79=0,"",H79/ABS(F79)) -> 0.54831316 | J79: Bank overdraft interest decreased by KSh 26.047m (54.8%) compared with 2024. The reduction is consistent with the fall in the overdraft balance from KSh 404.420m to KSh 160.564m. Lower facility utilisation reduced the annual interest charge.
B80: Loan interest | F80: -96266.036 | G80: -67695.708 | H80: =G80-F80 -> 28570.328 | I80: =IF(F80=0,"",H80/ABS(F80)) -> 0.29678513 | J80: Loan interest decreased by KSh 28.570m (29.7%) compared with 2024. The decrease reflects lower outstanding term-loan balances and scheduled repayments. A year-end interest recovery also reduced the net charge.
B81: Other interest | F81: -3220.672 | G81: -1912.377 | H81: =G81-F81 -> 1308.295 | I81: =IF(F81=0,"",H81/ABS(F81)) -> 0.40621802 | J81: Other interest decreased by KSh 1.308m (40.6%) compared with 2024. This line mainly relates to loan appraisal or facility fees. The reduction indicates fewer or lower-value financing arrangements during the year.
B82: Lease liability interest | F82: -193729.2 | G82: -196102.38 | H82: =G82-F82 -> -2373.179 | I82: =IF(F82=0,"",H82/ABS(F82)) -> -0.012249981 | J82: Lease liability interest increased by KSh 2.373m (1.2%) compared with 2024. The increase is consistent with the larger combined lease-liability balance following new lease additions. The charge should agree to the IFRS 16 lease schedules.
B83: Penalties and interest | F83: 112.351 | G83: -1808.406 | H83: =G83-F83 -> -1920.757 | I83: =IF(F83=0,"",H83/ABS(F83)) -> -17.096038 | J83: Penalties and interest moved from a credit of KSh 0.112m in 2024 to a charge of KSh 1.808m in 2025. A small prior-year credit changed to a financing-related charge in 2025. The entries should be reviewed to distinguish statutory penalties from ordinary borrowing costs.
B84: Exchange differences - realised | F84: 28292.662 | G84: 174.12 | H84: =G84-F84 -> -28118.542 | I84: =IF(F84=0,"",H84/ABS(F84)) -> -0.99384575 | J84: Exchange differences - realised decreased by KSh 28.119m (99.4%) compared with 2024. Financing-related realised exchange gains fell sharply, removing a material offset against interest expense. The reduction reflects fewer favourable settlements or less foreign-currency exposure.
B85: Exchange differences - unrealised | F85: 35311.754 | G85: 836.81347 | H85: =G85-F85 -> -34474.941 | I85: =IF(F85=0,"",H85/ABS(F85)) -> -0.97630213 | J85: Exchange differences - unrealised decreased by KSh 34.475m (97.6%) compared with 2024. The year-end financing revaluation gain reduced substantially, removing a non-cash benefit recorded in 2024. The balance should agree to the foreign-currency loan revaluation.
B86: Loss before tax | F86: =SUM('Profit and Loss'!F76,'Profit and Loss'!F78) -> -117091.84 | G86: =SUM('Profit and Loss'!G76,'Profit and Loss'!G78) -> -48091.218 | H86: =G86-F86 -> 69000.624 | I86: =IF(F86=0,"",H86/ABS(F86)) -> 0.58928635 | J86: Loss before tax decreased by KSh 69.001m (58.9%) compared with 2024. Operating profit improved by KSh 79.963m, partly offset by KSh 10.962m of additional finance costs. The result was a KSh 69.001m narrowing of the pre-tax loss.
B88: Tax charge | F88: =SUM('Profit and Loss'!F89,'Profit and Loss'!F90) -> -378.202 | G88: =SUM('Profit and Loss'!G89,'Profit and Loss'!G90) -> -423.535 | H88: =G88-F88 -> -45.333 | I88: =IF(F88=0,"",H88/ABS(F88)) -> -0.11986452 | J88: Tax charge increased by KSh 0.045m (12.0%) compared with 2024. The tax charge moved broadly in line with interest income despite the overall accounting loss. The amount approximates tax on taxable interest and should agree to the current-tax computation.
B89: Current year tax charge | F89: -378.202 | G89: -423.535 | H89: =G89-F89 -> -45.333 | I89: =IF(F89=0,"",H89/ABS(F89)) -> -0.11986452 | J89: Current year tax charge increased by KSh 0.045m (12.0%) compared with 2024. The increase follows the rise in interest income from KSh 1.261m to KSh 1.412m. The amount should agree to the current-tax computation and instalment-tax records.
B90: Deferred tax charge / credit | F90: 0 | G90: 0 | H90: =G90-F90 -> 0 | I90: =IF(F90=0,"",H90/ABS(F90)) | J90: No balance was recorded for deferred tax charge / credit in either year. No deferred-tax charge or credit was recognised in either year. Deferred-tax assets appear to remain offset by the unrecognised-asset adjustment.
B91: Loss for the year | F91: =SUM('Profit and Loss'!F86,'Profit and Loss'!F88) -> -117470.04 | G91: =SUM('Profit and Loss'!G86,'Profit and Loss'!G88) -> -48514.753 | H91: =G91-F91 -> 68955.291 | I91: =IF(F91=0,"",H91/ABS(F91)) -> 0.58700319 | J91: Loss for the year decreased by KSh 68.955m (58.7%) compared with 2024. The loss narrowed mainly because operating profit improved by KSh 79.963m. Higher finance costs and the slightly higher tax charge absorbed part of that improvement.
B93: OTHER COMPREHENSIVE INCOME
B94: Re-measurement of staff gratuity | F94: -1114 | G94: -10091.547 | H94: =G94-F94 -> -8977.547 | I94: =IF(F94=0,"",H94/ABS(F94)) -> -8.0588393 | J94: Re-measurement of staff gratuity increased by KSh 8.978m (805.9%) compared with 2024. The larger actuarial loss reflects changes in the gratuity obligation at year end. The amount should agree to the actuarial valuation and is recognised outside profit or loss.
B95: Other comprehensive loss | F95: =SUM('Profit and Loss'!F94) -> -1114 | G95: =SUM('Profit and Loss'!G94) -> -10091.547 | H95: =G95-F95 -> -8977.547 | I95: =IF(F95=0,"",H95/ABS(F95)) -> -8.0588393 | J95: Other comprehensive loss increased by KSh 8.978m (805.9%) compared with 2024. The increase is entirely attributable to the larger gratuity remeasurement loss. It is presented outside operating profit and finance costs.
B96: Total comprehensive loss | F96: =SUM('Profit and Loss'!F91,'Profit and Loss'!F95) -> -118584.04 | G96: =SUM('Profit and Loss'!G91,'Profit and Loss'!G95) -> -58606.3 | H96: =G96-F96 -> 59977.744 | I96: =IF(F96=0,"",H96/ABS(F96)) -> 0.50578258 | J96: Total comprehensive loss decreased by KSh 59.978m (50.6%) compared with 2024. The KSh 68.955m improvement in the annual loss was partly offset by the KSh 8.978m increase in other comprehensive loss. Total comprehensive loss therefore improved by KSh 59.978m.

Sheet Balance Sheet
B2: Demo Café Group
B3: Balance sheet (KSh '000)
B4: Account / breakdown | F4: 2024 | G4: 2025 | H4: Variance | I4: Variance % | J4: Remarks
B5: CAPITAL EMPLOYED
B6: Share capital | F6: 1000 | G6: 1000 | H6: =G6-F6 -> 0 | I6: =IF(F6=0,"",H6/ABS(F6)) -> 0 | J6: Share capital decreased by KSh 0.000m (0.0%) compared with 2024. No new ordinary shares were issued during the year; the increase in funding was recorded through preference shares instead.
B7: Preference share capital - nominal | F7: 134566 | G7: 186192 | H7: =G7-F7 -> 51626 | I7: =IF(F7=0,"",H7/ABS(F7)) -> 0.38364817 | J7: Preference share capital - nominal increased by KSh 51.626m (38.4%) compared with 2024. New preference-share allotments increased nominal capital by KSh 51.626m. Together with the related premium, the issue added KSh 516.260m of funding.
B8: Preference share capital - premium | F8: 1211094 | G8: 1675728 | H8: =G8-F8 -> 464634 | I8: =IF(F8=0,"",H8/ABS(F8)) -> 0.38364817 | J8: Preference share capital - premium increased by KSh 464.634m (38.4%) compared with 2024. The increase is the premium component of the 2025 preference-share allotments. It should agree to allotment records, shareholder resolutions and cash receipts.
B9: Shareholders funds awaiting allotment | F9: 0.13 | G9: 5.603 | H9: =G9-F9 -> 5.473 | I9: =IF(F9=0,"",H9/ABS(F9)) -> 42.1 | J9: Shareholders funds awaiting allotment increased by KSh 0.005m (4,210.0%) compared with 2024. The closing balance is small and represents funding not yet allocated to share capital. It should be agreed to the share-allotment reconciliation.
B10: Accumulated deficit | F10: =SUM('Balance Sheet'!F11,'Profit and Loss'!F91,'Profit and Loss'!F95) -> -2891043.9 | G10: =SUM('Balance Sheet'!G11,'Profit and Loss'!G91,'Profit and Loss'!G95) -> -2949650.2 | H10: =G10-F10 -> -58606.3 | I10: =IF(F10=0,"",H10/ABS(F10)) -> -0.020271674 | J10: Accumulated deficit increased by KSh 58.606m (2.0%) compared with 2024. The deficit increased by the KSh 48.515m loss for the year and KSh 10.092m other comprehensive loss. These movements total the KSh 58.606m increase.
B11: Accumulated deficit at start of year | F11: -2772459.8 | G11: -2891043.9 | H11: =G11-F11 -> -118584.04 | I11: =IF(F11=0,"",H11/ABS(F11)) -> -0.042772141 | J11: Accumulated deficit at start of year increased by KSh 118.584m (4.3%) compared with 2024. The movement represents the prior-year total comprehensive loss carried into the 2025 opening balance. It should agree to the prior-year closing equity position.
B12: Loss for the year | F12: ='Profit and Loss'!F91 -> -117470.04 | G12: ='Profit and Loss'!G91 -> -48514.753 | H12: =G12-F12 -> 68955.291 | I12: =IF(F12=0,"",H12/ABS(F12)) -> 0.58700319 | J12: Loss for the year decreased by KSh 68.955m (58.7%) compared with 2024. The loss narrowed as operating profit improved, although finance costs remained significant. The amount agrees to the profit and loss statement.
B13: Other comprehensive loss | F13: ='Profit and Loss'!F95 -> -1114 | G13: ='Profit and Loss'!G95 -> -10091.547 | H13: =G13-F13 -> -8977.547 | I13: =IF(F13=0,"",H13/ABS(F13)) -> -8.0588393 | J13: Other comprehensive loss increased by KSh 8.978m (805.9%) compared with 2024. The increase reflects the larger actuarial remeasurement loss on staff gratuity. The amount should agree to the actuarial valuation.
B14: Shareholders deficit | F14: =SUM('Balance Sheet'!F6,'Balance Sheet'!F7,'Balance Sheet'!F8,'Balance Sheet'!F9,'Balance Sheet'!F10) -> -1544383.7 | G14: =SUM('Balance Sheet'!G6,'Balance Sheet'!G7,'Balance Sheet'!G8,'Balance Sheet'!G9,'Balance Sheet'!G10) -> -1086724.6 | H14: =G14-F14 -> 457659.17 | I14: =IF(F14=0,"",H14/ABS(F14)) -> 0.29633773 | J14: Shareholders deficit decreased by KSh 457.659m (29.6%) compared with 2024. Preference-share funding of KSh 516.260m more than offset the KSh 58.606m total comprehensive loss. This reduced the shareholders’ deficit by KSh 457.659m.
B16: Non-current liabilities
B17: Borrowings | F17: =SUM('Balance Sheet'!F18,'Balance Sheet'!F19) -> 385671.11 | G17: =SUM('Balance Sheet'!G18,'Balance Sheet'!G19) -> 286140.18 | H17: =G17-F17 -> -99530.923 | I17: =IF(F17=0,"",H17/ABS(F17)) -> -0.25807202 | J17: Borrowings decreased by KSh 99.531m (25.8%) compared with 2024. The reduction mainly reflects the fall in bank overdraft and non-current term-loan balances. Current term-loan instalments partly offset this decrease.
B18: Term loans | F18: 384458.08 | G18: 283040.72 | H18: =G18-F18 -> -101417.36 | I18: =IF(F18=0,"",H18/ABS(F18)) -> -0.26379302 | J18: Term loans decreased by KSh 101.417m (26.4%) compared with 2024. Scheduled repayments reduced the total loan exposure, while amounts due within twelve months were reclassified to current liabilities. The balance should agree to lender statements and amortisation schedules.
B19: Finance lease | F19: 1213.024 | G19: 3099.461 | H19: =G19-F19 -> 1886.437 | I19: =IF(F19=0,"",H19/ABS(F19)) -> 1.5551522 | J19: Finance lease increased by KSh 1.886m (155.5%) compared with 2024. The movement reflects changes in hire-purchase or finance-lease facilities and the split between current and non-current portions. It should agree to the underlying repayment schedules.
B20: Lease liabilities | F20: 898775.77 | G20: 1050523.7 | H20: =G20-F20 -> 151747.97 | I20: =IF(F20=0,"",H20/ABS(F20)) -> 0.16883852 | J20: Lease liabilities increased by KSh 151.748m (16.9%) compared with 2024. New leases increased the longer-term liability, while payments, concessions and modifications reduced the balance. The movement should agree to the IFRS 16 lease roll-forward.
B21: Total non-current liabilities | F21: =SUM('Balance Sheet'!F17,'Balance Sheet'!F20) -> 1284446.9 | G21: =SUM('Balance Sheet'!G17,'Balance Sheet'!G20) -> 1336663.9 | H21: =G21-F21 -> 52217.045 | I21: =IF(F21=0,"",H21/ABS(F21)) -> 0.040653331 | J21: Total non-current liabilities increased by KSh 52.217m (4.1%) compared with 2024. The KSh 151.748m increase in non-current lease liabilities exceeded the KSh 99.531m reduction in non-current borrowings. This produced a net KSh 52.217m increase.
B22: Total capital employed | F22: =SUM('Balance Sheet'!F14,'Balance Sheet'!F21) -> -259936.87 | G22: =SUM('Balance Sheet'!G14,'Balance Sheet'!G21) -> 249939.35 | H22: =G22-F22 -> 509876.22 | I22: =IF(F22=0,"",H22/ABS(F22)) -> 1.9615387 | J22: Total capital employed moved from a charge of KSh 259.937m in 2024 to a credit of KSh 249.939m in 2025. Additional preference-share funding and non-current liabilities moved the balance into a positive position. The change also incorporates the current-year comprehensive loss.
B24: REPRESENTED BY
B25: Non-current assets
B26: Property, plant and equipment | F26: 630019 | G26: 584861 | H26: =G26-F26 -> -45158 | I26: =IF(F26=0,"",H26/ABS(F26)) -> -0.071677203 | J26: Property, plant and equipment decreased by KSh 45.158m (7.2%) compared with 2024. Additions were outweighed by depreciation and disposals, reducing the net carrying amount. The balance should agree to the fixed-asset register.
B27: Leasehold improvements | F27: 278548 | G27: 226244 | H27: =G27-F27 -> -52304 | I27: =IF(F27=0,"",H27/ABS(F27)) -> -0.18777374 | J27: Leasehold improvements decreased by KSh 52.304m (18.8%) compared with 2024. Depreciation and disposals exceeded additions and transfers from work in progress. This reduced the closing carrying value materially.
B28: Buildings | F28: 0 | G28: 0 | H28: =G28-F28 -> 0 | I28: =IF(F28=0,"",H28/ABS(F28)) | J28: No balance was recorded for buildings in either year. The building asset had already been disposed of, with no additions or remaining carrying value in either year.
B29: Motor vehicles | F29: 4526 | G29: 5348 | H29: =G29-F29 -> 822 | I29: =IF(F29=0,"",H29/ABS(F29)) -> 0.18161732 | J29: Motor vehicles increased by KSh 0.822m (18.2%) compared with 2024. Current-year additions exceeded depreciation, producing a modest increase in carrying value. Disposals had little remaining net book value.
B30: Furniture, fittings and equipment | F30: 74759 | G30: 65624 | H30: =G30-F30 -> -9135 | I30: =IF(F30=0,"",H30/ABS(F30)) -> -0.12219265 | J30: Furniture, fittings and equipment decreased by KSh 9.135m (12.2%) compared with 2024. Depreciation and disposals exceeded additions and transfers from work in progress. The movement should agree to the asset register.
B31: Computer equipment | F31: 11871 | G31: 12780 | H31: =G31-F31 -> 909 | I31: =IF(F31=0,"",H31/ABS(F31)) -> 0.076573161 | J31: Computer equipment increased by KSh 0.909m (7.7%) compared with 2024. Additions exceeded depreciation, resulting in a modest net increase. The balance should be supported by invoices and the asset register.
B32: Kitchen equipment | F32: 85476 | G32: 81142 | H32: =G32-F32 -> -4334 | I32: =IF(F32=0,"",H32/ABS(F32)) -> -0.050704291 | J32: Kitchen equipment decreased by KSh 4.334m (5.1%) compared with 2024. Additions and transfers were insufficient to offset depreciation and disposals. The carrying amount therefore reduced despite investment during the year.
B33: Communications and office equipment | F33: 112885 | G33: 88888 | H33: =G33-F33 -> -23997 | I33: =IF(F33=0,"",H33/ABS(F33)) -> -0.21257917 | J33: Communications and office equipment decreased by KSh 23.997m (21.3%) compared with 2024. Depreciation exceeded additions, and disposals further reduced the balance. This indicates an ageing asset base despite current-year purchases.
B34: Cutlery | F34: 25626 | G34: 27160 | H34: =G34-F34 -> 1534 | I34: =IF(F34=0,"",H34/ABS(F34)) -> 0.059861079 | J34: Cutlery increased by KSh 1.534m (6.0%) compared with 2024. Additions and transfers slightly exceeded depreciation and disposals. The balance remained broadly stable relative to the expanded network.
B35: Capital work in progress | F35: 36328 | G35: 77675 | H35: =G35-F35 -> 41347 | I35: =IF(F35=0,"",H35/ABS(F35)) -> 1.1381579 | J35: Capital work in progress increased by KSh 41.347m (113.8%) compared with 2024. The increase reflects capital purchases not yet available for use at year end. Transfers to operating asset classes partly offset additions.
B36: Right-of-use assets | F36: =SUM('Balance Sheet'!F37,'Balance Sheet'!F38) -> 923547.25 | G36: =SUM('Balance Sheet'!G37,'Balance Sheet'!G38) -> 1157167.7 | H36: =G36-F36 -> 233620.45 | I36: =IF(F36=0,"",H36/ABS(F36)) -> 0.25295993 | J36: Right-of-use assets increased by KSh 233.620m (25.3%) compared with 2024. New leases and modifications increased gross cost, while depreciation reduced the net balance. The movement should agree to the lease roll-forward.
B37: Cost at year end | F37: 2597976.6 | G37: 3129223.8 | H37: =G37-F37 -> 531247.25 | I37: =IF(F37=0,"",H37/ABS(F37)) -> 0.20448501 | J37: Cost at year end increased by KSh 531.247m (20.4%) compared with 2024. The increase reflects additions during the year and should agree to the relevant fixed-asset or lease roll-forward.
B38: Less: accumulated depreciation | F38: -1674429.3 | G38: -1972056.1 | H38: =G38-F38 -> -297626.81 | I38: =IF(F38=0,"",H38/ABS(F38)) -> -0.17774821 | J38: Less: accumulated depreciation increased by KSh 297.627m (17.8%) compared with 2024. The higher accumulated charge reflects the current-year depreciation or amortisation expense, net of amounts removed on disposals.
B39: Intangible assets - computer software | F39: =SUM('Balance Sheet'!F40,'Balance Sheet'!F41) -> 1735.287 | G39: =SUM('Balance Sheet'!G40,'Balance Sheet'!G41) -> 15504.74 | H39: =G39-F39 -> 13769.453 | I39: =IF(F39=0,"",H39/ABS(F39)) -> 7.9349716 | J39: Intangible assets - computer software increased by KSh 13.769m (793.5%) compared with 2024. Software additions materially increased the asset base, with amortisation only partly offsetting the growth. The balance should agree to the intangible-asset register.
B40: Cost at year end | F40: 29101.206 | G40: 47169.409 | H40: =G40-F40 -> 18068.203 | I40: =IF(F40=0,"",H40/ABS(F40)) -> 0.62087472 | J40: Cost at year end increased by KSh 18.068m (62.1%) compared with 2024. The increase reflects additions during the year and should agree to the relevant fixed-asset or lease roll-forward.
B41: Less: accumulated amortisation | F41: -27365.919 | G41: -31664.669 | H41: =G41-F41 -> -4298.75 | I41: =IF(F41=0,"",H41/ABS(F41)) -> -0.15708407 | J41: Less: accumulated amortisation increased by KSh 4.299m (15.7%) compared with 2024. The higher accumulated charge reflects the current-year depreciation or amortisation expense, net of amounts removed on disposals.
B42: Intangible assets - acquired trademarks | F42: =SUM('Balance Sheet'!F43,'Balance Sheet'!F44) -> 0 | G42: =SUM('Balance Sheet'!G43,'Balance Sheet'!G44) -> 0 | H42: =G42-F42 -> 0 | I42: =IF(F42=0,"",H42/ABS(F42)) | J42: No balance was recorded for intangible assets - acquired trademarks in either year. The trademarks were fully impaired in the prior year and had no remaining carrying value in 2025.
B43: Carrying amount at start of year | F43: 18500 | G43: 0 | H43: =G43-F43 -> -18500 | I43: =IF(F43=0,"",H43/ABS(F43)) -> -1 | J43: Carrying amount at start of year was nil in 2025, compared with KSh 18.500m in 2024. The prior-year carrying amount was fully impaired, leaving no opening balance for 2025.
B44: Impairment during the year | F44: -18500 | G44: 0 | H44: =G44-F44 -> 18500 | I44: =IF(F44=0,"",H44/ABS(F44)) -> 1 | J44: Impairment during the year was nil in 2025, compared with KSh 18.500m in 2024. No further charge arose because the trademark asset had already been fully impaired in 2024.
B45: Deferred tax | F45: 0 | G45: 0 | H45: =G45-F45 -> 0 | I45: =IF(F45=0,"",H45/ABS(F45)) | J45: No balance was recorded for deferred tax in either year. No net deferred-tax asset was recognised because temporary differences and tax losses were fully offset by the unrecognised-asset adjustment.
B46: Property and equipment | F46: -94962 | G46: -98318 | H46: =G46-F46 -> -3356 | I46: =IF(F46=0,"",H46/ABS(F46)) -> -0.035340452 | J46: Property and equipment increased by KSh 3.356m (3.5%) compared with 2024. This temporary difference changed with the underlying accounting balance. The tax effect remains unrecognised through the offsetting deferred-tax adjustment.
B47: Leave provision | F47: -7845 | G47: -7989 | H47: =G47-F47 -> -144 | I47: =IF(F47=0,"",H47/ABS(F47)) -> -0.018355641 | J47: Leave provision increased by KSh 0.144m (1.8%) compared with 2024. This temporary difference changed with the underlying accounting balance. The tax effect remains unrecognised through the offsetting deferred-tax adjustment.
B48: Bad debts provision | F48: -1515 | G48: -2601 | H48: =G48-F48 -> -1086 | I48: =IF(F48=0,"",H48/ABS(F48)) -> -0.71683168 | J48: Bad debts provision increased by KSh 1.086m (71.7%) compared with 2024. This temporary difference changed with the underlying accounting balance. The tax effect remains unrecognised through the offsetting deferred-tax adjustment.
B49: Gratuity provision | F49: -18303 | G49: -22884 | H49: =G49-F49 -> -4581 | I49: =IF(F49=0,"",H49/ABS(F49)) -> -0.25028684 | J49: Gratuity provision increased by KSh 4.581m (25.0%) compared with 2024. The increase reflects service cost, interest cost and actuarial loss, partly offset by benefits paid. The closing obligation should agree to the actuarial report.
B50: Right-of-use asset differences | F50: -209542 | G50: -219198 | H50: =G50-F50 -> -9656 | I50: =IF(F50=0,"",H50/ABS(F50)) -> -0.046081454 | J50: Right-of-use asset differences increased by KSh 9.656m (4.6%) compared with 2024. This temporary difference changed with the underlying accounting balance. The tax effect remains unrecognised through the offsetting deferred-tax adjustment.
B51: Foreign exchange differences | F51: -1967 | G51: -2434 | H51: =G51-F51 -> -467 | I51: =IF(F51=0,"",H51/ABS(F51)) -> -0.23741739 | J51: Foreign exchange differences increased by KSh 0.467m (23.7%) compared with 2024. This temporary difference changed with the underlying accounting balance. The tax effect remains unrecognised through the offsetting deferred-tax adjustment.
B52: Tax losses | F52: -222901.54 | G52: -224278.09 | H52: =G52-F52 -> -1376.5448 | I52: =IF(F52=0,"",H52/ABS(F52)) -> -0.0061755733 | J52: Tax losses increased by KSh 1.377m (0.6%) compared with 2024. Tax losses increased slightly, but the related deferred-tax asset remains unrecognised. The balance should agree to the tax computation.
B53: Offset for deferred tax assets not recognised | F53: 557035.54 | G53: 577702.09 | H53: =G53-F53 -> 20666.545 | I53: =IF(F53=0,"",H53/ABS(F53)) -> 0.037100945 | J53: Offset for deferred tax assets not recognised increased by KSh 20.667m (3.7%) compared with 2024. The offset increased to match the larger net deferred-tax asset arising from temporary differences and tax losses. This keeps recognised deferred tax at nil.
B54: Total non-current assets | F54: =SUM('Balance Sheet'!F26,'Balance Sheet'!F36,'Balance Sheet'!F39,'Balance Sheet'!F42,'Balance Sheet'!F45) -> 1555301.5 | G54: =SUM('Balance Sheet'!G26,'Balance Sheet'!G36,'Balance Sheet'!G39,'Balance Sheet'!G42,'Balance Sheet'!G45) -> 1757533.4 | H54: =G54-F54 -> 202231.9 | I54: =IF(F54=0,"",H54/ABS(F54)) -> 0.13002745 | J54: Total non-current assets increased by KSh 202.232m (13.0%) compared with 2024. Growth in right-of-use assets and software more than offset the reduction in property, plant and equipment. This produced a KSh 202.232m net increase.
B56: Current assets
B57: Inventories | F57: 124312.2 | G57: 157057.37 | H57: =G57-F57 -> 32745.176 | I57: =IF(F57=0,"",H57/ABS(F57)) -> 0.26341081 | J57: Inventories increased by KSh 32.745m (26.3%) compared with 2024. The increase was mainly driven by food, beverages and tobacco, packaging-related stock and spare parts. The movement is consistent with the larger trading network.
B58: Food, beverages and tobacco | F58: 85000.246 | G58: 106716.46 | H58: =G58-F58 -> 21716.219 | I58: =IF(F58=0,"",H58/ABS(F58)) -> 0.25548419 | J58: Food, beverages and tobacco increased by KSh 21.716m (25.5%) compared with 2024. The higher balance is consistent with increased sales volumes and stock requirements across more outlets. Cut-off, ageing and net realisable value should be reviewed.
B59: Cleaning materials | F59: 2876.28 | G59: 2849.463 | H59: =G59-F59 -> -26.817 | I59: =IF(F59=0,"",H59/ABS(F59)) -> -0.0093235012 | J59: Cleaning materials decreased by KSh 0.027m (0.9%) compared with 2024. The balance was broadly unchanged, indicating stable stock holdings despite the larger outlet network.
B60: Packaging, staff uniforms and stationery | F60: 23028.626 | G60: 27336.815 | H60: =G60-F60 -> 4308.189 | I60: =IF(F60=0,"",H60/ABS(F60)) -> 0.18707972 | J60: Packaging, staff uniforms and stationery increased by KSh 4.308m (18.7%) compared with 2024. The increase is consistent with higher stock requirements for a wider operating network. The balance should agree to year-end counts and ageing reports.
B61: Spare parts | F61: 13407.045 | G61: 20154.371 | H61: =G61-F61 -> 6747.326 | I61: =IF(F61=0,"",H61/ABS(F61)) -> 0.5032672 | J61: Spare parts increased by KSh 6.747m (50.3%) compared with 2024. The significant increase may reflect stocking for maintenance of a larger asset base. Slow-moving and obsolete items should be assessed.
B62: Trade and other receivables | F62: 121693.44 | G62: 139408.53 | H62: =G62-F62 -> 17715.093 | I62: =IF(F62=0,"",H62/ABS(F62)) -> 0.14557147 | J62: Trade and other receivables increased by KSh 17.715m (14.6%) compared with 2024. Higher trade receivables, prepayments, other receivables and director balances were partly offset by lower deposits and a larger loss allowance.
B63: Trade receivables | F63: 36841.907 | G63: 52764.761 | H63: =G63-F63 -> 15922.854 | I63: =IF(F63=0,"",H63/ABS(F63)) -> 0.43219408 | J63: Trade receivables increased by KSh 15.923m (43.2%) compared with 2024. The balance grew substantially faster than revenue, indicating slower collections or higher credit sales. Ageing, subsequent receipts and impairment should receive particular attention.
B64: Prepayments | F64: 13607.155 | G64: 18201.633 | H64: =G64-F64 -> 4594.478 | I64: =IF(F64=0,"",H64/ABS(F64)) -> 0.33765163 | J64: Prepayments increased by KSh 4.594m (33.8%) compared with 2024. The increase likely reflects advance payments for rent, insurance, services or supplies. The balance should be supported by schedules and released over the correct periods.
B65: Deposits | F65: 61093.234 | G65: 58601.427 | H65: =G65-F65 -> -2491.807 | I65: =IF(F65=0,"",H65/ABS(F65)) -> -0.040786955 | J65: Deposits decreased by KSh 2.492m (4.1%) compared with 2024. The reduction suggests refunds, utilisation or reclassification of deposits. Remaining balances should be confirmed and assessed for recoverability.
B66: Other receivables | F66: 9786.995 | G66: 11254.538 | H66: =G66-F66 -> 1467.543 | I66: =IF(F66=0,"",H66/ABS(F66)) -> 0.14994827 | J66: Other receivables increased by KSh 1.468m (15.0%) compared with 2024. The increase should be analysed by counterparty and nature, with subsequent recovery tested for older items.
B67: Receivables from directors | F67: 5276.984 | G67: 6781.547 | H67: =G67-F67 -> 1504.563 | I67: =IF(F67=0,"",H67/ABS(F67)) -> 0.28511798 | J67: Receivables from directors increased by KSh 1.505m (28.5%) compared with 2024. The balance increased and should be agreed to director confirmations, approvals and related-party disclosures.
B68: Less: expected credit loss provision | F68: -4912.835 | G68: -8195.373 | H68: =G68-F68 -> -3282.538 | I68: =IF(F68=0,"",H68/ABS(F68)) -> -0.66815556 | J68: Less: expected credit loss provision increased by KSh 3.283m (66.8%) compared with 2024. The larger allowance is consistent with the growth in receivables and potentially older outstanding balances. It should agree to the impairment model and ageing data.
... B70: Tax recoverable | F70: 19080.679 | G70: 19314.293 | H70: =G70-F70 -> 233.614 | I70: =IF(F70=0,"",H70/ABS(F70)) -> 0.012243485 | J70: Tax recoverable increased by KSh 0.234m (1.2%) compared with 2024. The balance was broadly stable and should agree to tax returns, payment records and the tax authority ledger.
B71: Total current assets | F71: =SUM('Balance Sheet'!F57,'Balance Sheet'!F62,'Balance Sheet'!F69,'Balance Sheet'!F70) -> 316708.06 | G71: =SUM('Balance Sheet'!G57,'Balance Sheet'!G62,'Balance Sheet'!G69,'Balance Sheet'!G70) -> 356919.64 | H71: =G71-F71 -> 40211.583 | I71: =IF(F71=0,"",H71/ABS(F71)) -> 0.12696735 | J71: Total current assets increased by KSh 40.212m (12.7%) compared with 2024. Inventory and receivable growth more than offset the decrease in cash. The result was a KSh 40.212m increase in current assets.
B73: Current liabilities
B74: Borrowings | F74: =SUM('Balance Sheet'!F75,'Balance Sheet'!F76,'Balance Sheet'!F77) -> 491556.35 | G74: =SUM('Balance Sheet'!G75,'Balance Sheet'!G76,'Balance Sheet'!G77) -> 262772.05 | H74: =G74-F74 -> -228784.3 | I74: =IF(F74=0,"",H74/ABS(F74)) -> -0.46542842 | J74: Borrowings decreased by KSh 228.784m (46.5%) compared with 2024. The reduction mainly reflects the fall in bank overdraft and non-current term-loan balances. Current term-loan instalments partly offset this decrease.
B75: Term loans | F75: 84055.622 | G75: 100108.41 | H75: =G75-F75 -> 16052.793 | I75: =IF(F75=0,"",H75/ABS(F75)) -> 0.19097822 | J75: Term loans increased by KSh 16.053m (19.1%) compared with 2024. Scheduled repayments reduced the total loan exposure, while amounts due within twelve months were reclassified to current liabilities. The balance should agree to lender statements and amortisation schedules.
B76: Finance lease | F76: 3080.739 | G76: 2100.082 | H76: =G76-F76 -> -980.657 | I76: =IF(F76=0,"",H76/ABS(F76)) -> -0.31831875 | J76: Finance lease decreased by KSh 0.981m (31.8%) compared with 2024. The movement reflects changes in hire-purchase or finance-lease facilities and the split between current and non-current portions. It should agree to the underlying repayment schedules.
B77: Bank overdraft | F77: 404419.99 | G77: 160563.56 | H77: =G77-F77 -> -243856.43 | I77: =IF(F77=0,"",H77/ABS(F77)) -> -0.60297819 | J77: Bank overdraft decreased by KSh 243.856m (60.3%) compared with 2024. The substantial reduction indicates repayment or lower utilisation of short-term facilities. This is consistent with the fall in overdraft interest.
B78: Trade and other payables | F78: =ROUND(SUM('Balance Sheet'!F79,'Balance Sheet'!F80,'Balance Sheet'!F81,'Balance Sheet'!F82,'Balance Sheet'!F83),0) -> 1121811 | G78: =ROUND(SUM('Balance Sheet'!G79,'Balance Sheet'!G80,'Balance Sheet'!G81,'Balance Sheet'!G82,'Balance Sheet'!G83),0) -> 1065169 | H78: =G78-F78 -> -56642 | I78: =IF(F78=0,"",H78/ABS(F78)) -> -0.050491571 | J78: Trade and other payables decreased by KSh 56.642m (5.0%) compared with 2024. Lower trade payables, grants and other payables outweighed the increase in accruals. The balance should be tested for completeness using subsequent payments.
B79: Trade payables | F79: 766022.53 | G79: 705275.56 | H79: =G79-F79 -> -60746.965 | I79: =IF(F79=0,"",H79/ABS(F79)) -> -0.0793018 | J79: Trade payables decreased by KSh 60.747m (7.9%) compared with 2024. The decrease may reflect supplier settlements or lower unpaid purchases at year end. Supplier statements and subsequent payments should be reconciled.
B80: Grants | F80: 41682.601 | G80: 36119.059 | H80: =G80-F80 -> -5563.542 | I80: =IF(F80=0,"",H80/ABS(F80)) -> -0.13347396 | J80: Grants decreased by KSh 5.564m (13.3%) compared with 2024. The reduction reflects utilisation or release of grant balances. The remaining amount should be agreed to grant conditions and supporting schedules.
B81: Accruals | F81: 138629.48 | G81: 164137.76 | H81: =G81-F81 -> 25508.282 | I81: =IF(F81=0,"",H81/ABS(F81)) -> 0.18400331 | J81: Accruals increased by KSh 25.508m (18.4%) compared with 2024. The increase indicates more costs incurred but unpaid at year end. Major accruals should be supported by invoices, contracts and post-year-end settlements.
B82: Other payables | F82: 175476.16 | G82: 159636.32 | H82: =G82-F82 -> -15839.836 | I82: =IF(F82=0,"",H82/ABS(F82)) -> -0.090267739 | J82: Other payables decreased by KSh 15.840m (9.0%) compared with 2024. The reduction suggests settlement or reclassification of miscellaneous obligations. Aged balances should be investigated.
B83: Payable to related parties | F83: 0 | G83: 0 | H83: =G83-F83 -> 0 | I83: =IF(F83=0,"",H83/ABS(F83)) | J83: No balance was recorded for payable to related parties in either year. No related-party payable was recorded in either year. This should be consistent with related-party confirmations and disclosures.
B84: Lease liabilities | F84: 457569.89 | G84: 450200.69 | H84: =G84-F84 -> -7369.2006 | I84: =IF(F84=0,"",H84/ABS(F84)) -> -0.016105082 | J84: Lease liabilities decreased by KSh 7.369m (1.6%) compared with 2024. New leases increased the longer-term liability, while payments, concessions and modifications reduced the balance. The movement should agree to the IFRS 16 lease roll-forward.
B85: Gratuity provision | F85: 61009.54 | G85: 86372.218 | H85: =G85-F85 -> 25362.678 | I85: =IF(F85=0,"",H85/ABS(F85)) -> 0.41571659 | J85: Gratuity provision increased by KSh 25.363m (41.6%) compared with 2024. The increase reflects service cost, interest cost and actuarial loss, partly offset by benefits paid. The closing obligation should agree to the actuarial report.
B86: Opening benefit obligation | F86: 55554.54 | G86: 61009.54 | H86: =G86-F86 -> 5455 | I86: =IF(F86=0,"",H86/ABS(F86)) -> 0.098191795 | J86: Opening benefit obligation increased by KSh 5.455m (9.8%) compared with 2024. The opening amount agrees to the prior-year closing gratuity obligation, adjusted for the roll-forward into 2025.
B87: Current service cost | F87: 4341 | G87: 6226.809 | H87: =G87-F87 -> 1885.809 | I87: =IF(F87=0,"",H87/ABS(F87)) -> 0.43441811 | J87: Current service cost increased by KSh 1.886m (43.4%) compared with 2024. The increase is consistent with employee service earned during the year and changes in the covered workforce.
B88: Interest cost | F88: 0 | G88: 10022.322 | H88: =G88-F88 -> 10022.322 | I88: =IF(F88=0,"",H88/ABS(F88)) | J88: Interest cost was recorded at KSh 10.022m in 2025, with no comparable amount in 2024. A separate finance component was recognised on the opening benefit obligation in 2025. It should agree to the actuarial discount-rate calculation.
B89: Actuarial loss | F89: 1114 | G89: 10091.547 | H89: =G89-F89 -> 8977.547 | I89: =IF(F89=0,"",H89/ABS(F89)) -> 8.0588393 | J89: Actuarial loss increased by KSh 8.978m (805.9%) compared with 2024. The larger loss reflects changes in actuarial assumptions or experience adjustments. It is recognised in other comprehensive income.
B90: Benefits and expenses paid | F90: 0 | G90: -978 | H90: =G90-F90 -> -978 | I90: =IF(F90=0,"",H90/ABS(F90)) | J90: Benefits and expenses paid was recorded at KSh 0.978m in 2025, with no comparable amount in 2024. Payments during the year reduced the closing gratuity obligation. They should be agreed to payroll and bank records.
B91: Total current liabilities | F91: =SUM('Balance Sheet'!F74,'Balance Sheet'!F78,'Balance Sheet'!F84,'Balance Sheet'!F85) -> 2131946.8 | G91: =SUM('Balance Sheet'!G74,'Balance Sheet'!G78,'Balance Sheet'!G84,'Balance Sheet'!G85) -> 1864514 | H91: =G91-F91 -> -267432.82 | I91: =IF(F91=0,"",H91/ABS(F91)) -> -0.12544066 | J91: Total current liabilities decreased by KSh 267.433m (12.5%) compared with 2024. The reduction was mainly driven by the KSh 228.784m fall in current borrowings and KSh 56.642m reduction in trade and other payables. Higher gratuity provisions partly offset these movements.
B92: Net current liabilities | F92: ='Balance Sheet'!F71-'Balance Sheet'!F91 -> -1815238.7 | G92: ='Balance Sheet'!G71-'Balance Sheet'!G91 -> -1507594.3 | H92: =G92-F92 -> 307644.4 | I92: =IF(F92=0,"",H92/ABS(F92)) -> 0.16947876 | J92: Net current liabilities decreased by KSh 307.644m (16.9%) compared with 2024. Current liabilities reduced more than current assets increased, improving the working-capital deficit by KSh 307.644m. The business nevertheless remained in a net current liability position.
B93: Net assets / liabilities | F93: =SUM('Balance Sheet'!F54,'Balance Sheet'!F92) -> -259937.19 | G93: =SUM('Balance Sheet'!G54,'Balance Sheet'!G92) -> 249939.12 | H93: =G93-F93 -> 509876.3 | I93: =IF(F93=0,"",H93/ABS(F93)) -> 1.9615366 | J93: Net assets / liabilities moved from a charge of KSh 259.937m in 2024 to a credit of KSh 249.939m in 2025. Preference-share funding and the improved working-capital position moved the entity from net liabilities to net assets. The closing balance agrees broadly to total capital employed.

Sheet Schedule of Expenses
B2: Demo Café Group
B3: Schedule of expenses (KSh '000)
B4: Account / breakdown | F4: 2024 | G4: 2025 | H4: Variance | I4: Variance % | J4: Remarks
B5: 1. COST OF SALES
B6: Food costs | F6: 1460153.8 | G6: 1496095.2 | H6: =G6-F6 -> 35941.318 | I6: =IF(F6=0,"",H6/ABS(F6)) -> 0.024614748 | J6: Food costs increased by KSh 35.941m (2.5%) compared with 2024. The movement reflects higher consumption as sales and the outlet network expanded. Costs grew more slowly than revenue, improving food-cost absorption during the year.
B7: Lighting, water and heating | F7: 233482.13 | G7: 226081.31 | H7: =G7-F7 -> -7400.82 | I7: =IF(F7=0,"",H7/ABS(F7)) -> -0.031697586 | J7: Lighting, water and heating decreased by KSh 7.401m (3.2%) compared with 2024. Utility costs reduced despite higher sales, indicating improved consumption or tariff management. The cost represented a lower proportion of revenue than in 2024.
B8: Depreciation - kitchen equipment | F8: 45877.086 | G8: 43082.723 | H8: =G8-F8 -> -2794.363 | I8: =IF(F8=0,"",H8/ABS(F8)) -> -0.060909775 | J8: Depreciation - kitchen equipment decreased by KSh 2.794m (6.1%) compared with 2024. The lower charge is consistent with disposals and the changing age profile of kitchen assets. Current-year additions partly offset the reduction in the depreciable base.
B9: Packaging materials | F9: 83870.664 | G9: 78766.514 | H9: =G9-F9 -> -5104.15 | I9: =IF(F9=0,"",H9/ABS(F9)) -> -0.060857393 | J9: Packaging materials decreased by KSh 5.104m (6.1%) compared with 2024. Packaging costs fell despite revenue growth, suggesting better purchasing, stock control or lower packaging intensity. This provided a favourable offset within cost of sales.
B10: Salaries | F10: 202715.31 | G10: 223870.54 | H10: =G10-F10 -> 21155.221 | I10: =IF(F10=0,"",H10/ABS(F10)) -> 0.10435926 | J10: Salaries increased by KSh 21.155m (10.4%) compared with 2024. Production payroll rose as the business operated a broader outlet network. The increase was above food-sales growth, indicating a higher staffing run rate during the year.
B11: Total cost of sales | F11: =SUM('Schedule of Expenses'!F6,'Schedule of Expenses'!F7,'Schedule of Expenses'!F8,'Schedule of Expenses'!F9,'Schedule of Expenses'!F10) -> 2026099 | G11: =SUM('Schedule of Expenses'!G6,'Schedule of Expenses'!G7,'Schedule of Expenses'!G8,'Schedule of Expenses'!G9,'Schedule of Expenses'!G10) -> 2067896.2 | H11: =G11-F11 -> 41797.206 | I11: =IF(F11=0,"",H11/ABS(F11)) -> 0.020629399 | J11: Total cost of sales increased by KSh 41.797m (2.1%) compared with 2024. Food costs and production salaries increased by KSh 35.941m and KSh 21.155m respectively. Lower utilities, packaging and kitchen depreciation partly offset the increase.
B13: 2. SALES AND MARKETING EXPENSES
B14: Advertising costs | F14: 55650.826 | G14: 81846.882 | H14: =G14-F14 -> 26196.056 | I14: =IF(F14=0,"",H14/ABS(F14)) -> 0.47072178 | J14: Advertising costs increased by KSh 26.196m (47.1%) compared with 2024. The increase reflects heavier campaign activity, including outlet launches, airport-location marketing, consultancy support and billboards. The scale of growth was well above revenue growth and should be supported by campaign documentation.
B15: Delivery costs | F15: 59531.207 | G15: 72400.102 | H15: =G15-F15 -> 12868.895 | I15: =IF(F15=0,"",H15/ABS(F15)) -> 0.21617057 | J15: Delivery costs increased by KSh 12.869m (21.6%) compared with 2024. The movement is consistent with higher delivery volumes and platform commissions. Delivery charges remained concentrated among the major delivery platforms.
B16: Total sales and marketing expenses | F16: =SUM('Schedule of Expenses'!F14,'Schedule of Expenses'!F15) -> 115182.03 | G16: =SUM('Schedule of Expenses'!G14,'Schedule of Expenses'!G15) -> 154246.98 | H16: =G16-F16 -> 39064.951 | I16: =IF(F16=0,"",H16/ABS(F16)) -> 0.33915837 | J16: Total sales and marketing expenses increased by KSh 39.065m (33.9%) compared with 2024. Advertising and delivery costs increased by KSh 26.196m and KSh 12.869m respectively. The higher spend is consistent with expanded marketing activity and delivery volumes.
B18: 3. ADMINISTRATIVE EXPENSES
B19: Employment
B20: Salaries and wages | F20: =SUM('Schedule of Expenses'!F21,'Schedule of Expenses'!F22) -> 745941 | G20: =SUM('Schedule of Expenses'!G21,'Schedule of Expenses'!G22) -> 798708.54 | H20: =G20-F20 -> 52767.536 | I20: =IF(F20=0,"",H20/ABS(F20)) -> 0.070739557 | J20: Salaries and wages increased by KSh 52.768m (7.1%) compared with 2024. The increase was mainly driven by the KSh 46.022m rise in salaries excluding NSSF and KSh 6.745m in employer NSSF. This is consistent with a larger workforce and higher payroll run rate across the expanded network.
B21: Salaries excluding NSSF | F21: 715425.5 | G21: 761447.58 | H21: =G21-F21 -> 46022.081 | I21: =IF(F21=0,"",H21/ABS(F21)) -> 0.064328265 | J21: Salaries excluding NSSF increased by KSh 46.022m (6.4%) compared with 2024. The movement reflects the higher staffing requirement of the expanded outlet network. The year-end payroll run rate was above the level recorded at the start of the year.
B22: National Social Security Fund | F22: 30515.502 | G22: 37260.957 | H22: =G22-F22 -> 6745.455 | I22: =IF(F22=0,"",H22/ABS(F22)) -> 0.22105011 | J22: National Social Security Fund increased by KSh 6.745m (22.1%) compared with 2024. Employer contributions rose faster than base salaries, consistent with statutory contribution changes and a larger covered payroll. The contribution should be agreed to payroll and statutory returns.
B23: Staff welfare | F23: 9231.594 | G23: 9970.814 | H23: =G23-F23 -> 739.22 | I23: =IF(F23=0,"",H23/ABS(F23)) -> 0.080075012 | J23: Staff welfare increased by KSh 0.739m (8.0%) compared with 2024. The increase is consistent with higher welfare and training needs for a larger workforce. The movement remained modest relative to total employment costs.
B24: Staff uniform | F24: 4975.708 | G24: 5053.69 | H24: =G24-F24 -> 77.982 | I24: =IF(F24=0,"",H24/ABS(F24)) -> 0.015672543 | J24: Staff uniform increased by KSh 0.078m (1.6%) compared with 2024. Uniform expenditure was broadly stable despite the wider outlet network. This suggests purchases were controlled or uniforms issued in prior periods continued to be used.
B25: Staff transport | F25: 42533.02 | G25: 45581.238 | H25: =G25-F25 -> 3048.218 | I25: =IF(F25=0,"",H25/ABS(F25)) -> 0.071667095 | J25: Staff transport increased by KSh 3.048m (7.2%) compared with 2024. The increase is consistent with additional staff and locations requiring transport support. Growth was broadly in line with revenue.
B26: Work permit expenses | F26: 940.016 | G26: 4685.898 | H26: =G26-F26 -> 3745.882 | I26: =IF(F26=0,"",H26/ABS(F26)) -> 3.984913 | J26: Work permit expenses increased by KSh 3.746m (398.5%) compared with 2024. The sharp increase reflects several significant permit-related payments during the year. The movement is concentrated and should be supported by the relevant permits and payment records.
B27: Net change in provision for leave | F27: -19101.286 | G27: 480.034 | H27: =G27-F27 -> 19581.32 | I27: =IF(F27=0,"",H27/ABS(F27)) -> 1.025131 | J27: Net change in provision for leave moved from a charge of KSh 19.101m in 2024 to a credit of KSh 0.480m in 2025. The prior-year leave-provision reversal did not recur. A small charge was recognised in 2025, creating an adverse year-on-year movement of KSh 19.581m.
B28: Provision for gratuity | F28: 4340.52 | G28: 5249.309 | H28: =G28-F28 -> 908.789 | I28: =IF(F28=0,"",H28/ABS(F28)) -> 0.2093733 | J28: Provision for gratuity increased by KSh 0.909m (20.9%) compared with 2024. The higher charge is consistent with an increased employee-benefit obligation and service cost. The final expense should agree to the actuarial report and gratuity reconciliation.
B29: Gratuity interest cost | F29: 0 | G29: 10022.322 | H29: =G29-F29 -> 10022.322 | I29: =IF(F29=0,"",H29/ABS(F29)) | J29: Gratuity interest cost was recorded at KSh 10.022m in 2025, with no comparable amount in 2024. A separate interest cost on the gratuity obligation was recognised for the first time in 2025. This added KSh 10.022m to employment costs and should agree to the actuarial valuation.
B30: Total employment costs | F30: =SUM('Schedule of Expenses'!F20,'Schedule of Expenses'!F23,'Schedule of Expenses'!F24,'Schedule of Expenses'!F25,'Schedule of Expenses'!F26,'Schedule of Expenses'!F27,'Schedule of Expenses'!F28,'Schedule of Expenses'!F29) -> 788860.57 | G30: =SUM('Schedule of Expenses'!G20,'Schedule of Expenses'!G23,'Schedule of Expenses'!G24,'Schedule of Expenses'!G25,'Schedule of Expenses'!G26,'Schedule of Expenses'!G27,'Schedule of Expenses'!G28,'Schedule of Expenses'!G29) -> 879751.84 | H30: =G30-F30 -> 90891.269 | I30: =IF(F30=0,"",H30/ABS(F30)) -> 0.11521842 | J30: Total employment costs increased by KSh 90.891m (11.5%) compared with 2024. The main drivers were the KSh 52.768m rise in salaries and NSSF, the KSh 19.581m leave-provision swing and the new KSh 10.022m gratuity interest charge. Together, these explain most of the increase.
B32: Other administration expenses
B33: Directors remuneration | F33: 47212.821 | G33: 61535.099 | H33: =G33-F33 -> 14322.279 | I33: =IF(F33=0,"",H33/ABS(F33)) -> 0.30335571 | J33: Directors remuneration increased by KSh 14.322m (30.3%) compared with 2024. The increase forms part of the overall rise in compensation costs. The balance should be agreed to approved remuneration schedules and related-party disclosures.
B34: Directors expenses | F34: 4080 | G34: 7055.7 | H34: =G34-F34 -> 2975.7 | I34: =IF(F34=0,"",H34/ABS(F34)) -> 0.72933824 | J34: Directors expenses increased by KSh 2.976m (72.9%) compared with 2024. The movement includes a director-related prior-period PAYE item recorded in 2025. This makes the increase partly non-recurring rather than purely current-year operating spend.
B35: Legal and professional fees | F35: 31278.778 | G35: 56211.184 | H35: =G35-F35 -> 24932.406 | I35: =IF(F35=0,"",H35/ABS(F35)) -> 0.79710294 | J35: Legal and professional fees increased by KSh 24.932m (79.7%) compared with 2024. The increase is consistent with a full year of e-commerce project support, website and catalogue services, and guest-experience roles. The balance also includes tax-related professional charges.
B36: Auditors remuneration
B37: Current year | F37: 3328.755 | G37: 4105.914 | H37: =G37-F37 -> 777.159 | I37: =IF(F37=0,"",H37/ABS(F37)) -> 0.23346837 | J37: Current year increased by KSh 0.777m (23.3%) compared with 2024. The audit fee increased broadly in line with the revised engagement charge. The balance should agree to the signed engagement letter and supplier invoices.
B38: Postages, telephones and internet | F38: 15203.122 | G38: 15463.742 | H38: =G38-F38 -> 260.62 | I38: =IF(F38=0,"",H38/ABS(F38)) -> 0.017142532 | J38: Postages, telephones and internet increased by KSh 0.261m (1.7%) compared with 2024. The modest increase is consistent with servicing more operating locations. Internet costs remain the largest component of this line.
B39: Printing and stationery | F39: 17635.862 | G39: 16174.117 | H39: =G39-F39 -> -1461.745 | I39: =IF(F39=0,"",H39/ABS(F39)) -> -0.082884806 | J39: Printing and stationery decreased by KSh 1.462m (8.3%) compared with 2024. The decrease is consistent with improved stock control and purchasing terms. The saving was achieved despite the larger operating network.
B40: Café decoration | F40: 1375.349 | G40: 5004.4 | H40: =G40-F40 -> 3629.051 | I40: =IF(F40=0,"",H40/ABS(F40)) -> 2.6386401 | J40: Café decoration increased by KSh 3.629m (263.9%) compared with 2024. The increase is consistent with decorating newly opened or refurbished outlets. The balance may also include timing effects from accruals and reversals around project completion.
B41: Motor vehicle running expenses | F41: 22056.853 | G41: 19606.944 | H41: =G41-F41 -> -2449.909 | I41: =IF(F41=0,"",H41/ABS(F41)) -> -0.11107246 | J41: Motor vehicle running expenses decreased by KSh 2.450m (11.1%) compared with 2024. The reduction is consistent with lower use of company vehicles after more logistics activity was outsourced. This saving was partly offset by higher travel and transport costs.
B42: Travelling and transport | F42: 30178.226 | G42: 46434.916 | H42: =G42-F42 -> 16256.69 | I42: =IF(F42=0,"",H42/ABS(F42)) -> 0.53868938 | J42: Travelling and transport increased by KSh 16.257m (53.9%) compared with 2024. The increase reflects the broader outlet network and greater use of outsourced logistics. Logistics-related charges appear to be the main component of the movement.
B43: Entertainment expenses | F43: -737.971 | G43: 0 | H43: =G43-F43 -> 737.971 | I43: =IF(F43=0,"",H43/ABS(F43)) -> 1 | J43: Entertainment expenses was nil in 2025, compared with KSh 0.738m in 2024. The prior-year balance did not recur, indicating that 2025 activities were either supplier-supported or offset by recoveries. The nil balance should be checked against the underlying gross entries.
B44: Bad debts / recoveries | F44: 11.941 | G44: 34.481 | H44: =G44-F44 -> 22.54 | I44: =IF(F44=0,"",H44/ABS(F44)) -> 1.8876141 | J44: Bad debts / recoveries increased by KSh 0.023m (188.8%) compared with 2024. More receivable balances were written off in 2025, although the amount remains immaterial. The write-offs should be matched to approved customer account closures.
B45: Cash sale shortages / surpluses | F45: -804.758 | G45: 256.535 | H45: =G45-F45 -> 1061.293 | I45: =IF(F45=0,"",H45/ABS(F45)) -> 1.3187728 | J45: Cash sale shortages / surpluses moved from a charge of KSh 0.805m in 2024 to a credit of KSh 0.257m in 2025. The prior-year net surplus changed to a net shortage in 2025. This indicates a deterioration in till or cash reconciliation outcomes and warrants review by outlet.
B46: Expected credit loss provision / reversal | F46: -1947.275 | G46: 3617.778 | H46: =G46-F46 -> 5565.053 | I46: =IF(F46=0,"",H46/ABS(F46)) -> 2.857867 | J46: Expected credit loss provision / reversal moved from a charge of KSh 1.947m in 2024 to a credit of KSh 3.618m in 2025. The movement from a reversal to a charge is consistent with the 43.2% increase in trade receivables. The provision should agree to the year-end ageing and expected-credit-loss model.
B47: Bank charges and commissions | F47: 43925.823 | G47: 44938.634 | H47: =G47-F47 -> 1012.811 | I47: =IF(F47=0,"",H47/ABS(F47)) -> 0.023057303 | J47: Bank charges and commissions increased by KSh 1.013m (2.3%) compared with 2024. The increase is consistent with higher card and mobile-money transaction volumes as sales grew. Charges rose more slowly than revenue, indicating improved processing-cost absorption.
B48: Penalties | F48: 681.689 | G48: 0 | H48: =G48-F48 -> -681.689 | I48: =IF(F48=0,"",H48/ABS(F48)) -> -1 | J48: Penalties was nil in 2025, compared with KSh 0.682m in 2024. No operating penalties were recorded in 2025, removing the prior-year charge. Any finance-related penalties are presented separately within finance costs.
... B51: Exchange differences - unrealised | F51: -1864.9076 | G51: 830.67247 | H51: =G51-F51 -> 2695.5801 | I51: =IF(F51=0,"",H51/ABS(F51)) -> 1.4454229 | J51: Exchange differences - unrealised moved from a charge of KSh 1.865m in 2024 to a credit of KSh 0.831m in 2025. The prior-year revaluation gain changed to a loss in 2025. This non-cash movement reflects year-end translation of outstanding foreign-currency balances.
B52: Total other administrative expenses | F52: =SUM('Schedule of Expenses'!F33,'Schedule of Expenses'!F34,'Schedule of Expenses'!F35,'Schedule of Expenses'!F38,'Schedule of Expenses'!F39,'Schedule of Expenses'!F40,'Schedule of Expenses'!F41,'Schedule of Expenses'!F42,'Schedule of Expenses'!F43,'Schedule of Expenses'!F44,'Schedule of Expenses'!F45,'Schedule of Expenses'!F46,'Schedule of Expenses'!F47,'Schedule of Expenses'!F48,'Schedule of Expenses'!F49,'Schedule of Expenses'!F50,'Schedule of Expenses'!F51,'Schedule of Expenses'!F37) -> 211403.18 | G52: =SUM('Schedule of Expenses'!G33,'Schedule of Expenses'!G34,'Schedule of Expenses'!G35,'Schedule of Expenses'!G38,'Schedule of Expenses'!G39,'Schedule of Expenses'!G40,'Schedule of Expenses'!G41,'Schedule of Expenses'!G42,'Schedule of Expenses'!G43,'Schedule of Expenses'!G44,'Schedule of Expenses'!G45,'Schedule of Expenses'!G46,'Schedule of Expenses'!G47,'Schedule of Expenses'!G48,'Schedule of Expenses'!G49,'Schedule of Expenses'!G50,'Schedule of Expenses'!G51,'Schedule of Expenses'!G37) -> 277547.85 | H52: =G52-F52 -> 66144.668 | I52: =IF(F52=0,"",H52/ABS(F52)) -> 0.31288397 | J52: Total other administrative expenses increased by KSh 66.145m (31.3%) compared with 2024. Professional fees, travel and directors’ remuneration were the largest increases. These were partly offset by lower motor-vehicle, printing and stationery costs and higher realised exchange gains.
B53: Total administrative expenses | F53: =SUM('Schedule of Expenses'!F30,'Schedule of Expenses'!F52) -> 1000263.8 | G53: =SUM('Schedule of Expenses'!G30,'Schedule of Expenses'!G52) -> 1157299.7 | H53: =G53-F53 -> 157035.94 | I53: =IF(F53=0,"",H53/ABS(F53)) -> 0.15699453 | J53: Total administrative expenses increased by KSh 157.036m (15.7%) compared with 2024. Employment costs increased by KSh 90.891m and other administration costs by KSh 66.145m. Payroll, professional services, travel and directors’ remuneration were the main drivers.
B55: 4. OTHER OPERATING EXPENSES
B56: Commercial rent | F56: 151640.2 | G56: 162816.41 | H56: =G56-F56 -> 11176.217 | I56: =IF(F56=0,"",H56/ABS(F56)) -> 0.073702206 | J56: Commercial rent increased by KSh 11.176m (7.4%) compared with 2024. The increase is consistent with additional operating locations and higher turnover-based rentals. Lower rent-concession credits also increased the net rental burden.
B57: Discount on rent concessions | F57: -33153.248 | G57: -29575.948 | H57: =G57-F57 -> 3577.3 | I57: =IF(F57=0,"",H57/ABS(F57)) -> 0.10790195 | J57: Discount on rent concessions decreased by KSh 3.577m (10.8%) compared with 2024. Rent-concession credits reduced in 2025, providing less relief against gross rental expense. This contributed to the increase in net occupancy costs.
B58: Repairs and maintenance | F58: 75611.803 | G58: 90080.999 | H58: =G58-F58 -> 14469.196 | I58: =IF(F58=0,"",H58/ABS(F58)) -> 0.19136161 | J58: Repairs and maintenance increased by KSh 14.469m (19.1%) compared with 2024. The increase is consistent with maintaining a larger and ageing outlet network. The balance includes both recurring maintenance contracts and ad hoc repairs.
B59: Licences | F59: 20231.739 | G59: 19863.963 | H59: =G59-F59 -> -367.776 | I59: =IF(F59=0,"",H59/ABS(F59)) -> -0.01817817 | J59: Licences decreased by KSh 0.368m (1.8%) compared with 2024. The slight reduction suggests lower effluent or other licence charges, partly offsetting the effect of additional locations. The account was broadly stable year on year.
B60: Lighting, water and heating | F60: 0 | G60: 0 | H60: =G60-F60 -> 0 | I60: =IF(F60=0,"",H60/ABS(F60)) | J60: No balance was recorded for lighting, water and heating in either year. Utility costs reduced despite higher sales, indicating improved consumption or tariff management. The cost represented a lower proportion of revenue than in 2024.
B61: Insurance expenses | F61: 26136.311 | G61: 27715.086 | H61: =G61-F61 -> 1578.775 | I61: =IF(F61=0,"",H61/ABS(F61)) -> 0.060405426 | J61: Insurance expenses increased by KSh 1.579m (6.0%) compared with 2024. The increase is consistent with insuring additional outlets and assets. Growth remained below the expansion in the right-of-use asset base.
B62: Security | F62: 9697.866 | G62: 12335.186 | H62: =G62-F62 -> 2637.32 | I62: =IF(F62=0,"",H62/ABS(F62)) -> 0.27194849 | J62: Security increased by KSh 2.637m (27.2%) compared with 2024. The movement reflects security services for additional locations. The increase was significant relative to revenue and should be supported by contracts and outlet listings.
B63: Cleaning expenses | F63: 42557.113 | G63: 43723.412 | H63: =G63-F63 -> 1166.299 | I63: =IF(F63=0,"",H63/ABS(F63)) -> 0.027405501 | J63: Cleaning expenses increased by KSh 1.166m (2.7%) compared with 2024. Cleaning costs increased only modestly despite the wider outlet network. This indicates relatively stable unit costs or efficiencies in service arrangements.
B64: Loss / gain on disposal of property and equipment | F64: -47584.405 | G64: 11198.99 | H64: =G64-F64 -> 58783.395 | I64: =IF(F64=0,"",H64/ABS(F64)) -> 1.23535 | J64: Loss / gain on disposal of property and equipment moved from a charge of KSh 47.584m in 2024 to a credit of KSh 11.199m in 2025. A disposal gain in 2024 changed to a loss in 2025, producing a KSh 58.783m adverse swing. The movement should agree to the fixed-asset disposal schedule and sale proceeds.
B65: Gain on lease termination | F65: -6604.337 | G65: -91196.041 | H65: =G65-F65 -> -84591.704 | I65: =IF(F65=0,"",H65/ABS(F65)) -> -12.808508 | J65: Gain on lease termination increased by KSh 84.592m (1,280.9%) compared with 2024. The larger gain reflects lease terminations or modifications where liabilities released exceeded the related right-of-use assets removed. The balance should agree to the lease modification calculations.
B66: Impairment of acquired trademarks | F66: 18500 | G66: 0 | H66: =G66-F66 -> -18500 | I66: =IF(F66=0,"",H66/ABS(F66)) -> -1 | J66: Impairment of acquired trademarks was nil in 2025, compared with KSh 18.500m in 2024. The trademarks were fully impaired in 2024, so no further charge arose in 2025. The nil closing carrying value explains the non-recurrence.
B67: Amortisation of intangible assets | F67: 1829.13 | G67: 6184.929 | H67: =G67-F67 -> 4355.799 | I67: =IF(F67=0,"",H67/ABS(F67)) -> 2.3813502 | J67: Amortisation of intangible assets increased by KSh 4.356m (238.1%) compared with 2024. The increase is consistent with additions to software and other intangible assets during the year. The charge should agree to the intangible-asset register and useful lives applied.
... B69: Depreciation of property, plant and equipment | F69: 191550.54 | G69: 176972.42 | H69: =G69-F69 -> -14578.116 | I69: =IF(F69=0,"",H69/ABS(F69)) -> -0.076105849 | J69: Depreciation of property, plant and equipment decreased by KSh 14.578m (7.6%) compared with 2024. The lower charge is consistent with disposals and fully depreciated assets, partly offset by current-year additions. The movement should agree to the fixed-asset register.
B70: Total other operating expenses | F70: =SUM('Schedule of Expenses'!F56,'Schedule of Expenses'!F57,'Schedule of Expenses'!F58,'Schedule of Expenses'!F59,'Schedule of Expenses'!F60,'Schedule of Expenses'!F61,'Schedule of Expenses'!F62,'Schedule of Expenses'!F63,'Schedule of Expenses'!F64,'Schedule of Expenses'!F65,'Schedule of Expenses'!F66,'Schedule of Expenses'!F67,'Schedule of Expenses'!F68,'Schedule of Expenses'!F69) -> 756470.76 | G70: =SUM('Schedule of Expenses'!G56,'Schedule of Expenses'!G57,'Schedule of Expenses'!G58,'Schedule of Expenses'!G59,'Schedule of Expenses'!G60,'Schedule of Expenses'!G61,'Schedule of Expenses'!G62,'Schedule of Expenses'!G63,'Schedule of Expenses'!G64,'Schedule of Expenses'!G65,'Schedule of Expenses'!G66,'Schedule of Expenses'!G67,'Schedule of Expenses'!G68,'Schedule of Expenses'!G69) -> 727746.22 | H70: =G70-F70 -> -28724.54 | I70: =IF(F70=0,"",H70/ABS(F70)) -> -0.037971779 | J70: Total other operating expenses decreased by KSh 28.725m (3.8%) compared with 2024. The larger gain on lease termination and the non-recurrence of trademark impairment reduced net costs. These benefits outweighed the adverse disposal movement and higher rent, repairs and security costs.

Sheet Branch Sales
C2: Demo Café Group
C3: Branch sales (KSh)
B6: Rank | C6: Branch | D6: January sales | E6: January % | F6: February sales | G6: February % | H6: March sales | I6: March % | J6: April sales | K6: April % | L6: May sales | M6: May % | N6: June sales | O6: June % | P6: July sales | Q6: July % | R6: August sales | S6: August % | T6: September sales | U6: September % | V6: October sales | W6: October % | X6: November sales | Y6: November % | Z6: December sales | AA6: December % | AB6: Total sales 2025 | AC6: % of annual sales
B7: =COUNTIFS($AB$7:$AB$75,">"&AB7)+1 -> 1 | C7: Branch 1 | D7: 14677352 | E7: =IF(D$83=0,"n.a.",D7/D$83) -> 0.042080448 | F7: 15642673 | G7: =IF(F$83=0,"n.a.",F7/F$83) -> 0.047550892 | H7: 15913418 | I7: =IF(H$83=0,"n.a.",H7/H$83) -> 0.047189524 | J7: 14525120 | K7: =IF(J$83=0,"n.a.",J7/J$83) -> 0.042459502 | L7: 16743537 | M7: =IF(L$83=0,"n.a.",L7/L$83) -> 0.047824834 | N7: 15469226 | O7: =IF(N$83=0,"n.a.",N7/N$83) -> 0.044461291 | P7: 14969772 | Q7: =IF(P$83=0,"n.a.",P7/P$83) -> 0.040412416 | R7: 15330888 | S7: =IF(R$83=0,"n.a.",R7/R$83) -> 0.04038593 | T7: 15250802 | U7: =IF(T$83=0,"n.a.",T7/T$83) -> 0.04207252 | V7: 16749196 | W7: =IF(V$83=0,"n.a.",V7/V$83) -> 0.044637058 | X7: 18034117 | Y7: =IF(X$83=0,"n.a.",X7/X$83) -> 0.048933274 | Z7: 20304771 | AA7: =IF(Z$83=0,"n.a.",Z7/Z$83) -> 0.046758453 | AB7: =SUM(D7,F7,H7,J7,L7,N7,P7,R7,T7,V7,X7,Z7) -> 1.9361087e+08 | AC7: =IF($AB$83=0,"n.a.",AB7/$AB$83) -> 0.044552791
B8: =COUNTIFS($AB$7:$AB$75,">"&AB8)+1 -> 2 | C8: Branch 2 | D8: 16117266 | E8: =IF(D$83=0,"n.a.",D8/D$83) -> 0.046208731 | F8: 14476606 | G8: =IF(F$83=0,"n.a.",F8/F$83) -> 0.044006259 | H8: 13117884 | I8: =IF(H$83=0,"n.a.",H8/H$83) -> 0.038899669 | J8: 14869920 | K8: =IF(J$83=0,"n.a.",J8/J$83) -> 0.043467414 | L8: 14757867 | M8: =IF(L$83=0,"n.a.",L8/L$83) -> 0.042153133 | N8: 14603871 | O8: =IF(N$83=0,"n.a.",N8/N$83) -> 0.041974108 | P8: 14908990 | Q8: =IF(P$83=0,"n.a.",P8/P$83) -> 0.04024833 | R8: 15288034 | S8: =IF(R$83=0,"n.a.",R8/R$83) -> 0.04027304 | T8: 14562154 | U8: =IF(T$83=0,"n.a.",T8/T$83) -> 0.040172741 | V8: 14546451 | W8: =IF(V$83=0,"n.a.",V8/V$83) -> 0.038766685 | X8: 14210296 | Y8: =IF(X$83=0,"n.a.",X8/X$83) -> 0.038557823 | Z8: 16513974 | AA8: =IF(Z$83=0,"n.a.",Z8/Z$83) -> 0.038028888 | AB8: =SUM(D8,F8,H8,J8,L8,N8,P8,R8,T8,V8,X8,Z8) -> 1.7797331e+08 | AC8: =IF($AB$83=0,"n.a.",AB8/$AB$83) -> 0.040954353
B9: =COUNTIFS($AB$7:$AB$75,">"&AB9)+1 -> 3 | C9: Branch 3 | D9: 14107338 | E9: =IF(D$83=0,"n.a.",D9/D$83) -> 0.040446202 | F9: 13614205 | G9: =IF(F$83=0,"n.a.",F9/F$83) -> 0.041384716 | H9: 15110608 | I9: =IF(H$83=0,"n.a.",H9/H$83) -> 0.04480888 | J9: 13651635 | K9: =IF(J$83=0,"n.a.",J9/J$83) -> 0.039906152 | L9: 14711147 | M9: =IF(L$83=0,"n.a.",L9/L$83) -> 0.042019687 | N9: 13755073 | O9: =IF(N$83=0,"n.a.",N9/N$83) -> 0.039534514 | P9: 14000426 | Q9: =IF(P$83=0,"n.a.",P9/P$83) -> 0.037795569 | R9: 13991403 | S9: =IF(R$83=0,"n.a.",R9/R$83) -> 0.036857345 | T9: 13739566 | U9: =IF(T$83=0,"n.a.",T9/T$83) -> 0.037903459 | V9: 14183290 | W9: =IF(V$83=0,"n.a.",V9/V$83) -> 0.037798849 | X9: 13823648 | Y9: =IF(X$83=0,"n.a.",X9/X$83) -> 0.037508703 | Z9: 14480186 | AA9: =IF(Z$83=0,"n.a.",Z9/Z$83) -> 0.033345419 | AB9: =SUM(D9,F9,H9,J9,L9,N9,P9,R9,T9,V9,X9,Z9) -> 1.6916853e+08 | AC9: =IF($AB$83=0,"n.a.",AB9/$AB$83) -> 0.038928238
B10: =COUNTIFS($AB$7:$AB$75,">"&AB10)+1 -> 4 | C10: Branch 4 | D10: 12314010 | E10: =IF(D$83=0,"n.a.",D10/D$83) -> 0.03530467 | F10: 12617769 | G10: =IF(F$83=0,"n.a.",F10/F$83) -> 0.038355731 | H10: 12991422 | I10: =IF(H$83=0,"n.a.",H10/H$83) -> 0.038524661 | J10: 12918517 | K10: =IF(J$83=0,"n.a.",J10/J$83) -> 0.037763118 | L10: 13534177 | M10: =IF(L$83=0,"n.a.",L10/L$83) -> 0.038657888 | N10: 13427561 | O10: =IF(N$83=0,"n.a.",N10/N$83) -> 0.038593185 | P10: 14127378 | Q10: =IF(P$83=0,"n.a.",P10/P$83) -> 0.03813829 | R10: 13459133 | S10: =IF(R$83=0,"n.a.",R10/R$83) -> 0.035455192 | T10: 13346415 | U10: =IF(T$83=0,"n.a.",T10/T$83) -> 0.036818871 | V10: 13787246 | W10: =IF(V$83=0,"n.a.",V10/V$83) -> 0.036743383 | X10: 13358618 | Y10: =IF(X$83=0,"n.a.",X10/X$83) -> 0.036246905 | Z10: 13508492 | AA10: =IF(Z$83=0,"n.a.",Z10/Z$83) -> 0.031107773 | AB10: =SUM(D10,F10,H10,J10,L10,N10,P10,R10,T10,V10,X10,Z10) -> 1.5939074e+08 | AC10: =IF($AB$83=0,"n.a.",AB10/$AB$83) -> 0.036678221
B11: =COUNTIFS($AB$7:$AB$75,">"&AB11)+1 -> 5 | C11: Branch 5 | D11: 10189243 | E11: =IF(D$83=0,"n.a.",D11/D$83) -> 0.029212894 | F11: 10957795 | G11: =IF(F$83=0,"n.a.",F11/F$83) -> 0.033309711 | H11: 11216205 | I11: =IF(H$83=0,"n.a.",H11/H$83) -> 0.033260445 | J11: 10850937 | K11: =IF(J$83=0,"n.a.",J11/J$83) -> 0.031719214 | L11: 11008657 | M11: =IF(L$83=0,"n.a.",L11/L$83) -> 0.031444206 | N11: 11912310 | O11: =IF(N$83=0,"n.a.",N11/N$83) -> 0.034238087 | P11: 12662523 | Q11: =IF(P$83=0,"n.a.",P11/P$83) -> 0.034183765 | R11: 12635665 | S11: =IF(R$83=0,"n.a.",R11/R$83) -> 0.033285944 | T11: 11726791 | U11: =IF(T$83=0,"n.a.",T11/T$83) -> 0.032350799 | V11: 12169924 | W11: =IF(V$83=0,"n.a.",V11/V$83) -> 0.032433175 | X11: 11586426 | Y11: =IF(X$83=0,"n.a.",X11/X$83) -> 0.031438287 | Z11: 13838734 | AA11: =IF(Z$83=0,"n.a.",Z11/Z$83) -> 0.031868263 | AB11: =SUM(D11,F11,H11,J11,L11,N11,P11,R11,T11,V11,X11,Z11) -> 1.4075521e+08 | AC11: =IF($AB$83=0,"n.a.",AB11/$AB$83) -> 0.032389904
B12: =COUNTIFS($AB$7:$AB$75,">"&AB12)+1 -> 6 | C12: Branch 6 | D12: 12153972 | E12: =IF(D$83=0,"n.a.",D12/D$83) -> 0.034845837 | F12: 10389376 | G12: =IF(F$83=0,"n.a.",F12/F$83) -> 0.03158182 | H12: 10506386 | I12: =IF(H$83=0,"n.a.",H12/H$83) -> 0.031155553 | J12: 11062156 | K12: =IF(J$83=0,"n.a.",J12/J$83) -> 0.032336645 | L12: 11344419 | M12: =IF(L$83=0,"n.a.",L12/L$83) -> 0.032403247 | N12: 10994385 | O12: =IF(N$83=0,"n.a.",N12/N$83) -> 0.031599809 | P12: 11536859 | Q12: =IF(P$83=0,"n.a.",P12/P$83) -> 0.031144921 | R12: 11951632 | S12: =IF(R$83=0,"n.a.",R12/R$83) -> 0.031484006 | T12: 10683754 | U12: =IF(T$83=0,"n.a.",T12/T$83) -> 0.029473363 | V12: 10884967 | W12: =IF(V$83=0,"n.a.",V12/V$83) -> 0.02900873 | X12: 11289457 | Y12: =IF(X$83=0,"n.a.",X12/X$83) -> 0.030632498 | Z12: 13541641 | AA12: =IF(Z$83=0,"n.a.",Z12/Z$83) -> 0.031184108 | AB12: =SUM(D12,F12,H12,J12,L12,N12,P12,R12,T12,V12,X12,Z12) -> 1.36339e+08 | AC12: =IF($AB$83=0,"n.a.",AB12/$AB$83) -> 0.031373668
B13: =COUNTIFS($AB$7:$AB$75,">"&AB13)+1 -> 7 | C13: Branch 7 | D13: 10672572 | E13: =IF(D$83=0,"n.a.",D13/D$83) -> 0.030598613 | F13: 9881591.5 | G13: =IF(F$83=0,"n.a.",F13/F$83) -> 0.030038247 | H13: 10403047 | I13: =IF(H$83=0,"n.a.",H13/H$83) -> 0.030849113 | J13: 10223369 | K13: =IF(J$83=0,"n.a.",J13/J$83) -> 0.02988472 | L13: 10026711 | M13: =IF(L$83=0,"n.a.",L13/L$83) -> 0.028639456 | N13: 9925307.7 | O13: =IF(N$83=0,"n.a.",N13/N$83) -> 0.02852709 | P13: 11011253 | Q13: =IF(P$83=0,"n.a.",P13/P$83) -> 0.029725995 | R13: 11465858 | S13: =IF(R$83=0,"n.a.",R13/R$83) -> 0.030204339 | T13: 10244080 | U13: =IF(T$83=0,"n.a.",T13/T$83) -> 0.028260431 | V13: 11024568 | W13: =IF(V$83=0,"n.a.",V13/V$83) -> 0.029380771 | X13: 11104801 | Y13: =IF(X$83=0,"n.a.",X13/X$83) -> 0.03013146 | Z13: 13760346 | AA13: =IF(Z$83=0,"n.a.",Z13/Z$83) -> 0.03168775 | AB13: =SUM(D13,F13,H13,J13,L13,N13,P13,R13,T13,V13,X13,Z13) -> 1.297435e+08 | AC13: =IF($AB$83=0,"n.a.",AB13/$AB$83) -> 0.029855944
B14: =COUNTIFS($AB$7:$AB$75,">"&AB14)+1 -> 8 | C14: Branch 8 | D14: 9486653.5 | E14: =IF(D$83=0,"n.a.",D14/D$83) -> 0.027198547 | F14: 8509185.6 | G14: =IF(F$83=0,"n.a.",F14/F$83) -> 0.025866382 | H14: 9443319.9 | I14: =IF(H$83=0,"n.a.",H14/H$83) -> 0.028003147 | J14: 9873089.1 | K14: =IF(J$83=0,"n.a.",J14/J$83) -> 0.028860791 | L14: 10015162 | M14: =IF(L$83=0,"n.a.",L14/L$83) -> 0.028606468 | N14: 10813549 | O14: =IF(N$83=0,"n.a.",N14/N$83) -> 0.031080052 | P14: 10673975 | Q14: =IF(P$83=0,"n.a.",P14/P$83) -> 0.028815479 | R14: 11634947 | S14: =IF(R$83=0,"n.a.",R14/R$83) -> 0.030649766 | T14: 9823612.9 | U14: =IF(T$83=0,"n.a.",T14/T$83) -> 0.027100486 | V14: 10737250 | W14: =IF(V$83=0,"n.a.",V14/V$83) -> 0.02861506 | X14: 11365924 | Y14: =IF(X$83=0,"n.a.",X14/X$83) -> 0.030839984 | Z14: 15163083 | AA14: =IF(Z$83=0,"n.a.",Z14/Z$83) -> 0.034918015 | AB14: =SUM(D14,F14,H14,J14,L14,N14,P14,R14,T14,V14,X14,Z14) -> 1.2753975e+08 | AC14: =IF($AB$83=0,"n.a.",AB14/$AB$83) -> 0.029348827
B15: =COUNTIFS($AB$7:$AB$75,">"&AB15)+1 -> 9 | C15: Branch 9 | D15: 10931530 | E15: =IF(D$83=0,"n.a.",D15/D$83) -> 0.031341055 | F15: 9338428.7 | G15: =IF(F$83=0,"n.a.",F15/F$83) -> 0.028387131 | H15: 8746298.7 | I15: =IF(H$83=0,"n.a.",H15/H$83) -> 0.025936206 | J15: 10522433 | K15: =IF(J$83=0,"n.a.",J15/J$83) -> 0.03075894 | L15: 9971056.3 | M15: =IF(L$83=0,"n.a.",L15/L$83) -> 0.028480489 | N15: 9691320.3 | O15: =IF(N$83=0,"n.a.",N15/N$83) -> 0.027854569 | P15: 11216681 | Q15: =IF(P$83=0,"n.a.",P15/P$83) -> 0.030280568 | R15: 12048699 | S15: =IF(R$83=0,"n.a.",R15/R$83) -> 0.031739709 | T15: 10566330 | U15: =IF(T$83=0,"n.a.",T15/T$83) -> 0.029149426 | V15: 10172732 | W15: =IF(V$83=0,"n.a.",V15/V$83) -> 0.027110604 | X15: 10346160 | Y15: =IF(X$83=0,"n.a.",X15/X$83) -> 0.028072983 | Z15: 11832218 | AA15: =IF(Z$83=0,"n.a.",Z15/Z$83) -> 0.027247597 | AB15: =SUM(D15,F15,H15,J15,L15,N15,P15,R15,T15,V15,X15,Z15) -> 1.2538389e+08 | AC15: =IF($AB$83=0,"n.a.",AB15/$AB$83) -> 0.02885273
B16: =COUNTIFS($AB$7:$AB$75,">"&AB16)+1 -> 10 | C16: Branch 10 | D16: 11735149 | E16: =IF(D$83=0,"n.a.",D16/D$83) -> 0.033645057 | F16: 10501309 | G16: =IF(F$83=0,"n.a.",F16/F$83) -> 0.031922075 | H16: 11017044 | I16: =IF(H$83=0,"n.a.",H16/H$83) -> 0.032669856 | J16: 10096941 | K16: =IF(J$83=0,"n.a.",J16/J$83) -> 0.029515151 | L16: 10602863 | M16: =IF(L$83=0,"n.a.",L16/L$83) -> 0.030285129 | N16: 10493261 | O16: =IF(N$83=0,"n.a.",N16/N$83) -> 0.030159487 | P16: 10261426 | Q16: =IF(P$83=0,"n.a.",P16/P$83) -> 0.02770176 | R16: 9717069.6 | S16: =IF(R$83=0,"n.a.",R16/R$83) -> 0.025597531 | T16: 9867408.2 | U16: =IF(T$83=0,"n.a.",T16/T$83) -> 0.027221304 | V16: 10470269 | W16: =IF(V$83=0,"n.a.",V16/V$83) -> 0.027903549 | X16: 10047915 | Y16: =IF(X$83=0,"n.a.",X16/X$83) -> 0.027263734 | Z16: 10352008 | AA16: =IF(Z$83=0,"n.a.",Z16/Z$83) -> 0.023838924 | AB16: =SUM(D16,F16,H16,J16,L16,N16,P16,R16,T16,V16,X16,Z16) -> 1.2516266e+08 | AC16: =IF($AB$83=0,"n.a.",AB16/$AB$83) -> 0.028801823
B17: =COUNTIFS($AB$7:$AB$75,">"&AB17)+1 -> 11 | C17: Branch 11 | D17: 9722190.8 | E17: =IF(D$83=0,"n.a.",D17/D$83) -> 0.02787384 | F17: 9399090.2 | G17: =IF(F$83=0,"n.a.",F17/F$83) -> 0.028571531 | H17: 10692453 | I17: =IF(H$83=0,"n.a.",H17/H$83) -> 0.031707315 | J17: 10007121 | K17: =IF(J$83=0,"n.a.",J17/J$83) -> 0.02925259 | L17: 10310329 | M17: =IF(L$83=0,"n.a.",L17/L$83) -> 0.029449559 | N17: 9921227.5 | O17: =IF(N$83=0,"n.a.",N17/N$83) -> 0.028515363 | P17: 10473007 | Q17: =IF(P$83=0,"n.a.",P17/P$83) -> 0.028272945 | R17: 10253538 | S17: =IF(R$83=0,"n.a.",R17/R$83) -> 0.027010741 | T17: 10169571 | U17: =IF(T$83=0,"n.a.",T17/T$83) -> 0.028054882 | V17: 10427164 | W17: =IF(V$83=0,"n.a.",V17/V$83) -> 0.027788672 | X17: 10475768 | Y17: =IF(X$83=0,"n.a.",X17/X$83) -> 0.028424659 | Z17: 11863735 | AA17: =IF(Z$83=0,"n.a.",Z17/Z$83) -> 0.027320176 | AB17: =SUM(D17,F17,H17,J17,L17,N17,P17,R17,T17,V17,X17,Z17) -> 1.2371519e+08 | AC17: =IF($AB$83=0,"n.a.",AB17/$AB$83) -> 0.028468738
B18: =COUNTIFS($AB$7:$AB$75,">"&AB18)+1 -> 12 | C18: Branch 12 | D18: 9209808.6 | E18: =IF(D$83=0,"n.a.",D18/D$83) -> 0.026404824 | F18: 8592004.8 | G18: =IF(F$83=0,"n.a.",F18/F$83) -> 0.026118137 | H18: 7833659.8 | I18: =IF(H$83=0,"n.a.",H18/H$83) -> 0.023229873 | J18: 9120905.3 | K18: =IF(J$83=0,"n.a.",J18/J$83) -> 0.026662025 | L18: 8291412.1 | M18: =IF(L$83=0,"n.a.",L18/L$83) -> 0.023682894 | N18: 10139099 | O18: =IF(N$83=0,"n.a.",N18/N$83) -> 0.029141563 | P18: 12323581 | Q18: =IF(P$83=0,"n.a.",P18/P$83) -> 0.033268756 | R18: 14307742 | S18: =IF(R$83=0,"n.a.",R18/R$83) -> 0.03769067 | T18: 9473309.2 | U18: =IF(T$83=0,"n.a.",T18/T$83) -> 0.0261341 | V18: 9875851.5 | W18: =IF(V$83=0,"n.a.",V18/V$83) -> 0.02631941 | X18: 8423071.8 | Y18: =IF(X$83=0,"n.a.",X18/X$83) -> 0.022854929 | Z18: 13236028 | AA18: =IF(Z$83=0,"n.a.",Z18/Z$83) -> 0.030480335 | AB18: =SUM(D18,F18,H18,J18,L18,N18,P18,R18,T18,V18,X18,Z18) -> 1.2082647e+08 | AC18: =IF($AB$83=0,"n.a.",AB18/$AB$83) -> 0.027804
... B43: =COUNTIFS($AB$7:$AB$75,">"&AB43)+1 -> 37 | C43: Branch 37 | D43: 4428546.6 | E43: =IF(D$83=0,"n.a.",D43/D$83) -> 0.012696788 | F43: 4314116.2 | G43: =IF(F$83=0,"n.a.",F43/F$83) -> 0.013114131 | H43: 4763964.5 | I43: =IF(H$83=0,"n.a.",H43/H$83) -> 0.014127023 | J43: 4918564.1 | K43: =IF(J$83=0,"n.a.",J43/J$83) -> 0.014377836 | L43: 4878333.8 | M43: =IF(L$83=0,"n.a.",L43/L$83) -> 0.013934064 | N43: 4685160.3 | O43: =IF(N$83=0,"n.a.",N43/N$83) -> 0.013465979 | P43: 5053123.1 | Q43: =IF(P$83=0,"n.a.",P43/P$83) -> 0.013641418 | R43: 4899978.6 | S43: =IF(R$83=0,"n.a.",R43/R$83) -> 0.01290794 | T43: 4634335.9 | U43: =IF(T$83=0,"n.a.",T43/T$83) -> 0.012784782 | V43: 5136794.4 | W43: =IF(V$83=0,"n.a.",V43/V$83) -> 0.013689695 | X43: 4905026.9 | Y43: =IF(X$83=0,"n.a.",X43/X$83) -> 0.013309164 | Z43: 5409359.6 | AA43: =IF(Z$83=0,"n.a.",Z43/Z$83) -> 0.01245684 | AB43: =SUM(D43,F43,H43,J43,L43,N43,P43,R43,T43,V43,X43,Z43) -> 58027304 | AC43: =IF($AB$83=0,"n.a.",AB43/$AB$83) -> 0.013352961
B44: =COUNTIFS($AB$7:$AB$75,">"&AB44)+1 -> 38 | C44: Branch 38 | L44: 206903.25 | M44: =IF(L$83=0,"n.a.",L44/L$83) -> 0.00059098109 | N44: 6393006 | O44: =IF(N$83=0,"n.a.",N44/N$83) -> 0.01837463 | P44: 6510135.2 | Q44: =IF(P$83=0,"n.a.",P44/P$83) -> 0.01757477 | R44: 6952322 | S44: =IF(R$83=0,"n.a.",R44/R$83) -> 0.018314398 | T44: 5441548.1 | U44: =IF(T$83=0,"n.a.",T44/T$83) -> 0.015011646 | V44: 5719362.7 | W44: =IF(V$83=0,"n.a.",V44/V$83) -> 0.015242256 | X44: 5152440.4 | Y44: =IF(X$83=0,"n.a.",X44/X$83) -> 0.013980489 | Z44: 7788723 | AA44: =IF(Z$83=0,"n.a.",Z44/Z$83) -> 0.017936112 | AB44: =SUM(D44,F44,H44,J44,L44,N44,P44,R44,T44,V44,X44,Z44) -> 44164441 | AC44: =IF($AB$83=0,"n.a.",AB44/$AB$83) -> 0.010162906
B45: =COUNTIFS($AB$7:$AB$75,">"&AB45)+1 -> 39 | C45: Branch 39 | D45: 3503121.2 | E45: =IF(D$83=0,"n.a.",D45/D$83) -> 0.010043563 | F45: 3208512.3 | G45: =IF(F$83=0,"n.a.",F45/F$83) -> 0.0097532959 | H45: 2468122 | I45: =IF(H$83=0,"n.a.",H45/H$83) -> 0.0073189496 | J45: 3408735.1 | K45: =IF(J$83=0,"n.a.",J45/J$83) -> 0.0099643374 | L45: 3493966.9 | M45: =IF(L$83=0,"n.a.",L45/L$83) -> 0.0099798741 | N45: 3344959.6 | O45: =IF(N$83=0,"n.a.",N45/N$83) -> 0.0096140056 | P45: 3694791.5 | Q45: =IF(P$83=0,"n.a.",P45/P$83) -> 0.0099744641 | R45: 3478128.7 | S45: =IF(R$83=0,"n.a.",R45/R$83) -> 0.0091623825 | T45: 3507838.5 | U45: =IF(T$83=0,"n.a.",T45/T$83) -> 0.0096771043 | V45: 3398428.2 | W45: =IF(V$83=0,"n.a.",V45/V$83) -> 0.0090569026 | X45: 3408157.7 | Y45: =IF(X$83=0,"n.a.",X45/X$83) -> 0.0092476006 | Z45: 3526654.3 | AA45: =IF(Z$83=0,"n.a.",Z45/Z$83) -> 0.0081212884 | AB45: =SUM(D45,F45,H45,J45,L45,N45,P45,R45,T45,V45,X45,Z45) -> 40441416 | AC45: =IF($AB$83=0,"n.a.",AB45/$AB$83) -> 0.0093061818
B46: =COUNTIFS($AB$7:$AB$75,">"&AB46)+1 -> 40 | C46: Branch 40 | D46: 2199674.1 | E46: =IF(D$83=0,"n.a.",D46/D$83) -> 0.0063065378 | F46: 2212948.5 | G46: =IF(F$83=0,"n.a.",F46/F$83) -> 0.0067269624 | H46: 3010367.6 | I46: =IF(H$83=0,"n.a.",H46/H$83) -> 0.0089269205 | J46: 2610442.8 | K46: =IF(J$83=0,"n.a.",J46/J$83) -> 0.0076307874 | L46: 2664638.8 | M46: =IF(L$83=0,"n.a.",L46/L$83) -> 0.0076110508 | N46: 2730251.8 | O46: =IF(N$83=0,"n.a.",N46/N$83) -> 0.0078472266 | P46: 2972476.8 | Q46: =IF(P$83=0,"n.a.",P46/P$83) -> 0.0080245026 | R46: 3047007.5 | S46: =IF(R$83=0,"n.a.",R46/R$83) -> 0.0080266863 | T46: 2566715.7 | U46: =IF(T$83=0,"n.a.",T46/T$83) -> 0.0070808209 | V46: 3293803.9 | W46: =IF(V$83=0,"n.a.",V46/V$83) -> 0.0087780761 | X46: 3189387.9 | Y46: =IF(X$83=0,"n.a.",X46/X$83) -> 0.0086539966 | Z46: 4110650.5 | AA46: =IF(Z$83=0,"n.a.",Z46/Z$83) -> 0.0094661329 | AB46: =SUM(D46,F46,H46,J46,L46,N46,P46,R46,T46,V46,X46,Z46) -> 34608366 | AC46: =IF($AB$83=0,"n.a.",AB46/$AB$83) -> 0.0079639087
B47: =COUNTIFS($AB$7:$AB$75,">"&AB47)+1 -> 41 | C47: Branch 41 | D47: 2666370.4 | E47: =IF(D$83=0,"n.a.",D47/D$83) -> 0.0076445713 | F47: 2819709.9 | G47: =IF(F$83=0,"n.a.",F47/F$83) -> 0.0085714071 | H47: 2262430.5 | I47: =IF(H$83=0,"n.a.",H47/H$83) -> 0.0067089938 | J47: 2963351.3 | K47: =IF(J$83=0,"n.a.",J47/J$83) -> 0.0086624017 | L47: 3181179.3 | M47: =IF(L$83=0,"n.a.",L47/L$83) -> 0.0090864538 | N47: 2405860.3 | O47: =IF(N$83=0,"n.a.",N47/N$83) -> 0.0069148682 | P47: 3228359.2 | Q47: =IF(P$83=0,"n.a.",P47/P$83) -> 0.0087152829 | R47: 2993711 | S47: =IF(R$83=0,"n.a.",R47/R$83) -> 0.0078862883 | T47: 2948335.2 | U47: =IF(T$83=0,"n.a.",T47/T$83) -> 0.0081335979 | V47: 2881550 | W47: =IF(V$83=0,"n.a.",V47/V$83) -> 0.0076794083 | X47: 2765464.4 | Y47: =IF(X$83=0,"n.a.",X47/X$83) -> 0.0075037343 | Z47: 2881452.8 | AA47: =IF(Z$83=0,"n.a.",Z47/Z$83) -> 0.0066354986 | AB47: =SUM(D47,F47,H47,J47,L47,N47,P47,R47,T47,V47,X47,Z47) -> 33997774 | AC47: =IF($AB$83=0,"n.a.",AB47/$AB$83) -> 0.0078234024
B48: =COUNTIFS($AB$7:$AB$75,">"&AB48)+1 -> 42 | C48: Branch 42 | D48: 2732208.9 | E48: =IF(D$83=0,"n.a.",D48/D$83) -> 0.0078333325 | F48: 2550889.5 | G48: =IF(F$83=0,"n.a.",F48/F$83) -> 0.0077542418 | H48: 3031329.9 | I48: =IF(H$83=0,"n.a.",H48/H$83) -> 0.0089890818 | J48: 2957075.1 | K48: =IF(J$83=0,"n.a.",J48/J$83) -> 0.0086440551 | L48: 3151413.1 | M48: =IF(L$83=0,"n.a.",L48/L$83) -> 0.0090014321 | N48: 3299693.7 | O48: =IF(N$83=0,"n.a.",N48/N$83) -> 0.0094839035 | P48: 3177151.2 | Q48: =IF(P$83=0,"n.a.",P48/P$83) -> 0.0085770418 | R48: 2895911.2 | S48: =IF(R$83=0,"n.a.",R48/R$83) -> 0.0076286558 | T48: 3078474.5 | U48: =IF(T$83=0,"n.a.",T48/T$83) -> 0.0084926141 | V48: 2274261.5 | W48: =IF(V$83=0,"n.a.",V48/V$83) -> 0.006060968 | AB48: =SUM(D48,F48,H48,J48,L48,N48,P48,R48,T48,V48,X48,Z48) -> 29148409 | AC48: =IF($AB$83=0,"n.a.",AB48/$AB$83) -> 0.0067074899
B49: =COUNTIFS($AB$7:$AB$75,">"&AB49)+1 -> 43 | C49: Branch 43 | D49: 2176844.8 | E49: =IF(D$83=0,"n.a.",D49/D$83) -> 0.0062410855 | F49: 1981761.4 | G49: =IF(F$83=0,"n.a.",F49/F$83) -> 0.0060241955 | H49: 2223282.1 | I49: =IF(H$83=0,"n.a.",H49/H$83) -> 0.0065929034 | J49: 2412152.2 | K49: =IF(J$83=0,"n.a.",J49/J$83) -> 0.0070511489 | L49: 2334022 | M49: =IF(L$83=0,"n.a.",L49/L$83) -> 0.0066667047 | N49: 2398372.5 | O49: =IF(N$83=0,"n.a.",N49/N$83) -> 0.0068933469 | P49: 2559143.4 | Q49: =IF(P$83=0,"n.a.",P49/P$83) -> 0.006908667 | R49: 2424048.3 | S49: =IF(R$83=0,"n.a.",R49/R$83) -> 0.0063856343 | T49: 2439410 | U49: =IF(T$83=0,"n.a.",T49/T$83) -> 0.0067296213 | V49: 2189880 | W49: =IF(V$83=0,"n.a.",V49/V$83) -> 0.0058360893 | X49: 2204731.2 | Y49: =IF(X$83=0,"n.a.",X49/X$83) -> 0.0059822565 | Z49: 2406634.6 | AA49: =IF(Z$83=0,"n.a.",Z49/Z$83) -> 0.0055420726 | AB49: =SUM(D49,F49,H49,J49,L49,N49,P49,R49,T49,V49,X49,Z49) -> 27750283 | AC49: =IF($AB$83=0,"n.a.",AB49/$AB$83) -> 0.00638576
B50: =COUNTIFS($AB$7:$AB$75,">"&AB50)+1 -> 44 | C50: Branch 44 | D50: 1872058.1 | E50: =IF(D$83=0,"n.a.",D50/D$83) -> 0.0053672521 | F50: 1764376 | G50: =IF(F$83=0,"n.a.",F50/F$83) -> 0.0053633832 | H50: 1947615.4 | I50: =IF(H$83=0,"n.a.",H50/H$83) -> 0.0057754434 | J50: 1821874.8 | K50: =IF(J$83=0,"n.a.",J50/J$83) -> 0.0053256633 | L50: 2101449 | M50: =IF(L$83=0,"n.a.",L50/L$83) -> 0.0060024026 | N50: 1955679.7 | O50: =IF(N$83=0,"n.a.",N50/N$83) -> 0.0056209695 | P50: 2149358.5 | Q50: =IF(P$83=0,"n.a.",P50/P$83) -> 0.0058024113 | R50: 2202291.9 | S50: =IF(R$83=0,"n.a.",R50/R$83) -> 0.0058014646 | T50: 2135346.5 | U50: =IF(T$83=0,"n.a.",T50/T$83) -> 0.0058907989 | V50: 2325908 | W50: =IF(V$83=0,"n.a.",V50/V$83) -> 0.0061986076 | X50: 2104197.8 | Y50: =IF(X$83=0,"n.a.",X50/X$83) -> 0.0057094719 | Z50: 2427281 | AA50: =IF(Z$83=0,"n.a.",Z50/Z$83) -> 0.0055896175 | AB50: =SUM(D50,F50,H50,J50,L50,N50,P50,R50,T50,V50,X50,Z50) -> 24807437 | AC50: =IF($AB$83=0,"n.a.",AB50/$AB$83) -> 0.0057085666
B51: =COUNTIFS($AB$7:$AB$75,">"&AB51)+1 -> 45 | C51: Branch 45 | T51: 1228250.1 | U51: =IF(T$83=0,"n.a.",T51/T$83) -> 0.003388384 | V51: 5304130 | W51: =IF(V$83=0,"n.a.",V51/V$83) -> 0.014135649 | X51: 5753190.2 | Y51: =IF(X$83=0,"n.a.",X51/X$83) -> 0.015610547 | Z51: 6202932.4 | AA51: =IF(Z$83=0,"n.a.",Z51/Z$83) -> 0.014284304 | AB51: =SUM(D51,F51,H51,J51,L51,N51,P51,R51,T51,V51,X51,Z51) -> 18488503 | AC51: =IF($AB$83=0,"n.a.",AB51/$AB$83) -> 0.0042544843
B52: =COUNTIFS($AB$7:$AB$75,">"&AB52)+1 -> 46 | C52: Branch 46 | D52: 2896187.9 | E52: =IF(D$83=0,"n.a.",D52/D$83) -> 0.0083034656 | F52: 2465978 | G52: =IF(F$83=0,"n.a.",F52/F$83) -> 0.0074961264 | H52: 2677944 | I52: =IF(H$83=0,"n.a.",H52/H$83) -> 0.007941154 | J52: 2704914.8 | K52: =IF(J$83=0,"n.a.",J52/J$83) -> 0.007906946 | L52: 2882571.1 | M52: =IF(L$83=0,"n.a.",L52/L$83) -> 0.0082335345 | N52: 1977627.7 | O52: =IF(N$83=0,"n.a.",N52/N$83) -> 0.0056840519 | AB52: =SUM(D52,F52,H52,J52,L52,N52,P52,R52,T52,V52,X52,Z52) -> 15605224 | AC52: =IF($AB$83=0,"n.a.",AB52/$AB$83) -> 0.0035909981
B53: =COUNTIFS($AB$7:$AB$75,">"&AB53)+1 -> 47 | C53: Branch 47 | D53: 3285139.6 | E53: =IF(D$83=0,"n.a.",D53/D$83) -> 0.009418603 | F53: 2977223.5 | G53: =IF(F$83=0,"n.a.",F53/F$83) -> 0.0090502198 | H53: 2831106.8 | I53: =IF(H$83=0,"n.a.",H53/H$83) -> 0.0083953419 | J53: 2767572.3 | K53: =IF(J$83=0,"n.a.",J53/J$83) -> 0.008090105 | L53: 2951750.2 | M53: =IF(L$83=0,"n.a.",L53/L$83) -> 0.0084311317 | N53: 671736.19 | O53: =IF(N$83=0,"n.a.",N53/N$83) -> 0.0019306886 | AB53: =SUM(D53,F53,H53,J53,L53,N53,P53,R53,T53,V53,X53,Z53) -> 15484529 | AC53: =IF($AB$83=0,"n.a.",AB53/$AB$83) -> 0.0035632244
B54: =COUNTIFS($AB$7:$AB$75,">"&AB54)+1 -> 48 | C54: Branch 48 | T54: 2334392.7 | U54: =IF(T$83=0,"n.a.",T54/T$83) -> 0.0064399093 | V54: 3439492.5 | W54: =IF(V$83=0,"n.a.",V54/V$83) -> 0.00916634 | X54: 3138955.6 | Y54: =IF(X$83=0,"n.a.",X54/X$83) -> 0.008517155 | Z54: 4697616.5 | AA54: =IF(Z$83=0,"n.a.",Z54/Z$83) -> 0.010817816 | AB54: =SUM(D54,F54,H54,J54,L54,N54,P54,R54,T54,V54,X54,Z54) -> 13610457 | AC54: =IF($AB$83=0,"n.a.",AB54/$AB$83) -> 0.0031319722
B55: =COUNTIFS($AB$7:$AB$75,">"&AB55)+1 -> 49 | C55: Branch 49 | D55: 985195.8 | E55: =IF(D$83=0,"n.a.",D55/D$83) -> 0.0028245887 | F55: 977120.5 | G55: =IF(F$83=0,"n.a.",F55/F$83) -> 0.0029702692 | H55: 961895.49 | I55: =IF(H$83=0,"n.a.",H55/H$83) -> 0.0028523973 | J55: 1124937.7 | K55: =IF(J$83=0,"n.a.",J55/J$83) -> 0.0032883924 | L55: 1009889.1 | M55: =IF(L$83=0,"n.a.",L55/L$83) -> 0.0028845626 | N55: 998889.83 | O55: =IF(N$83=0,"n.a.",N55/N$83) -> 0.0028709861 | P55: 1526576 | Q55: =IF(P$83=0,"n.a.",P55/P$83) -> 0.0041211466 | R55: 1426714 | S55: =IF(R$83=0,"n.a.",R55/R$83) -> 0.0037583715 | T55: 1008397.1 | U55: =IF(T$83=0,"n.a.",T55/T$83) -> 0.0027818739 | V55: 1038890.6 | W55: =IF(V$83=0,"n.a.",V55/V$83) -> 0.0027686714 | X55: 933960.11 | Y55: =IF(X$83=0,"n.a.",X55/X$83) -> 0.0025341815 | Z55: 1140082.9 | AA55: =IF(Z$83=0,"n.a.",Z55/Z$83) -> 0.002625418 | AB55: =SUM(D55,F55,H55,J55,L55,N55,P55,R55,T55,V55,X55,Z55) -> 13132549 | AC55: =IF($AB$83=0,"n.a.",AB55/$AB$83) -> 0.0030219983
B56: =COUNTIFS($AB$7:$AB$75,">"&AB56)+1 -> 50 | C56: Branch 50 | D56: 3070649.6 | E56: =IF(D$83=0,"n.a.",D56/D$83) -> 0.0088036531 | F56: 2685556.8 | G56: =IF(F$83=0,"n.a.",F56/F$83) -> 0.0081636058 | H56: 2386176.7 | I56: =IF(H$83=0,"n.a.",H56/H$83) -> 0.0070759498 | J56: 2307280 | K56: =IF(J$83=0,"n.a.",J56/J$83) -> 0.006744589 | AB56: =SUM(D56,F56,H56,J56,L56,N56,P56,R56,T56,V56,X56,Z56) -> 10449663 | AC56: =IF($AB$83=0,"n.a.",AB56/$AB$83) -> 0.0024046256
B57: =COUNTIFS($AB$7:$AB$75,">"&AB57)+1 -> 51 | C57: Branch 51 | D57: 726111.68 | E57: =IF(D$83=0,"n.a.",D57/D$83) -> 0.002081786 | F57: 698794.65 | G57: =IF(F$83=0,"n.a.",F57/F$83) -> 0.0021242091 | H57: 805079.95 | I57: =IF(H$83=0,"n.a.",H57/H$83) -> 0.0023873778 | J57: 828504.68 | K57: =IF(J$83=0,"n.a.",J57/J$83) -> 0.0024218662 | L57: 873968.25 | M57: =IF(L$83=0,"n.a.",L57/L$83) -> 0.0024963296 | N57: 918591.51 | O57: =IF(N$83=0,"n.a.",N57/N$83) -> 0.0026401945 | P57: 992950.43 | Q57: =IF(P$83=0,"n.a.",P57/P$83) -> 0.0026805703 | R57: 1084324.7 | S57: =IF(R$83=0,"n.a.",R57/R$83) -> 0.0028564203 | T57: 862037.3 | U57: =IF(T$83=0,"n.a.",T57/T$83) -> 0.0023781098 | V57: 912193.96 | W57: =IF(V$83=0,"n.a.",V57/V$83) -> 0.0024310215 | X57: 794238.62 | Y57: =IF(X$83=0,"n.a.",X57/X$83) -> 0.002155065 | Z57: 903380.43 | AA57: =IF(Z$83=0,"n.a.",Z57/Z$83) -> 0.0020803323 | AB57: =SUM(D57,F57,H57,J57,L57,N57,P57,R57,T57,V57,X57,Z57) -> 10400176 | AC57: =IF($AB$83=0,"n.a.",AB57/$AB$83) -> 0.0023932379
B58: =COUNTIFS($AB$7:$AB$75,">"&AB58)+1 -> 52 | C58: Branch 52 | D58: 889234.09 | E58: =IF(D$83=0,"n.a.",D58/D$83) -> 0.0025494633 | F58: 809077.4 | G58: =IF(F$83=0,"n.a.",F58/F$83) -> 0.0024594487 | H58: 838403.43 | I58: =IF(H$83=0,"n.a.",H58/H$83) -> 0.0024861949 | J58: 866530.84 | K58: =IF(J$83=0,"n.a.",J58/J$83) -> 0.0025330234 | L58: 892070.68 | M58: =IF(L$83=0,"n.a.",L58/L$83) -> 0.0025480359 | N58: 829516.46 | O58: =IF(N$83=0,"n.a.",N58/N$83) -> 0.0023841771 | P58: 788609.1 | Q58: =IF(P$83=0,"n.a.",P58/P$83) -> 0.0021289302 | R58: 837416.58 | S58: =IF(R$83=0,"n.a.",R58/R$83) -> 0.002205994 | T58: 822815.48 | U58: =IF(T$83=0,"n.a.",T58/T$83) -> 0.0022699082 | V58: 854431.25 | W58: =IF(V$83=0,"n.a.",V58/V$83) -> 0.0022770823 | X58: 824135.81 | Y58: =IF(X$83=0,"n.a.",X58/X$83) -> 0.0022361872 | Z58: 919826.41 | AA58: =IF(Z$83=0,"n.a.",Z58/Z$83) -> 0.0021182047 | AB58: =SUM(D58,F58,H58,J58,L58,N58,P58,R58,T58,V58,X58,Z58) -> 10172068 | AC58: =IF($AB$83=0,"n.a.",AB58/$AB$83) -> 0.0023407467
B59: =COUNTIFS($AB$7:$AB$75,">"&AB59)+1 -> 53 | C59: Branch 53 | D59: 731550.94 | E59: =IF(D$83=0,"n.a.",D59/D$83) -> 0.0020973805 | F59: 826724.32 | G59: =IF(F$83=0,"n.a.",F59/F$83) -> 0.0025130921 | H59: 782430.58 | I59: =IF(H$83=0,"n.a.",H59/H$83) -> 0.0023202135 | J59: 795433.74 | K59: =IF(J$83=0,"n.a.",J59/J$83) -> 0.002325194 | L59: 813259.79 | M59: =IF(L$83=0,"n.a.",L59/L$83) -> 0.0023229271 | N59: 819173.01 | O59: =IF(N$83=0,"n.a.",N59/N$83) -> 0.0023544482 | P59: 1010713.5 | Q59: =IF(P$83=0,"n.a.",P59/P$83) -> 0.0027285237 | R59: 835598.09 | S59: =IF(R$83=0,"n.a.",R59/R$83) -> 0.0022012036 | T59: 889861.98 | U59: =IF(T$83=0,"n.a.",T59/T$83) -> 0.0024548699 | V59: 798477.43 | W59: =IF(V$83=0,"n.a.",V59/V$83) -> 0.0021279639 | X59: 782533.89 | Y59: =IF(X$83=0,"n.a.",X59/X$83) -> 0.0021233057 | Z59: 596312.72 | AA59: =IF(Z$83=0,"n.a.",Z59/Z$83) -> 0.0013732073 | AB59: =SUM(D59,F59,H59,J59,L59,N59,P59,R59,T59,V59,X59,Z59) -> 9682070 | AC59: =IF($AB$83=0,"n.a.",AB59/$AB$83) -> 0.0022279908
B60: =COUNTIFS($AB$7:$AB$75,">"&AB60)+1 -> 54 | C60: Branch 54 | D60: 720913.51 | E60: =IF(D$83=0,"n.a.",D60/D$83) -> 0.0020668827 | F60: 645758.36 | G60: =IF(F$83=0,"n.a.",F60/F$83) -> 0.0019629884 | H60: 710033.45 | I60: =IF(H$83=0,"n.a.",H60/H$83) -> 0.0021055276 | J60: 718241.18 | K60: =IF(J$83=0,"n.a.",J60/J$83) -> 0.0020995464 | L60: 823965.01 | M60: =IF(L$83=0,"n.a.",L60/L$83) -> 0.0023535046 | N60: 728033.7 | O60: =IF(N$83=0,"n.a.",N60/N$83) -> 0.0020924977 | P60: 786329.55 | Q60: =IF(P$83=0,"n.a.",P60/P$83) -> 0.0021227763 | R60: 919240.76 | S60: =IF(R$83=0,"n.a.",R60/R$83) -> 0.0024215422 | T60: 784243.34 | U60: =IF(T$83=0,"n.a.",T60/T$83) -> 0.0021634989 | V60: 789886.25 | W60: =IF(V$83=0,"n.a.",V60/V$83) -> 0.0021050681 | X60: 884234.94 | Y60: =IF(X$83=0,"n.a.",X60/X$83) -> 0.0023992586 | Z60: 872747.95 | AA60: =IF(Z$83=0,"n.a.",Z60/Z$83) -> 0.0020097909 | AB60: =SUM(D60,F60,H60,J60,L60,N60,P60,R60,T60,V60,X60,Z60) -> 9383628 | AC60: =IF($AB$83=0,"n.a.",AB60/$AB$83) -> 0.0021593148
B61: =COUNTIFS($AB$7:$AB$75,">"&AB61)+1 -> 55 | C61: Branch 55 | D61: 581925 | E61: =IF(D$83=0,"n.a.",D61/D$83) -> 0.0016683981 | F61: 610859 | G61: =IF(F$83=0,"n.a.",F61/F$83) -> 0.0018569007 | H61: 563423.4 | I61: =IF(H$83=0,"n.a.",H61/H$83) -> 0.0016707713 | J61: 513726.25 | K61: =IF(J$83=0,"n.a.",J61/J$83) -> 0.001501713 | L61: 534610.37 | M61: =IF(L$83=0,"n.a.",L61/L$83) -> 0.0015270162 | N61: 565433.73 | O61: =IF(N$83=0,"n.a.",N61/N$83) -> 0.0016251566 | P61: 606763.93 | Q61: =IF(P$83=0,"n.a.",P61/P$83) -> 0.0016380207 | R61: 483824.57 | S61: =IF(R$83=0,"n.a.",R61/R$83) -> 0.0012745318 | T61: 624547.5 | U61: =IF(T$83=0,"n.a.",T61/T$83) -> 0.0017229446 | V61: 757248.69 | W61: =IF(V$83=0,"n.a.",V61/V$83) -> 0.0020180882 | X61: 710558.42 | Y61: =IF(X$83=0,"n.a.",X61/X$83) -> 0.0019280095 | Z61: 458673.35 | AA61: =IF(Z$83=0,"n.a.",Z61/Z$83) -> 0.0010562471 | AB61: =SUM(D61,F61,H61,J61,L61,N61,P61,R61,T61,V61,X61,Z61) -> 7011594.2 | AC61: =IF($AB$83=0,"n.a.",AB61/$AB$83) -> 0.0016134739
B62: =COUNTIFS($AB$7:$AB$75,">"&AB62)+1 -> 56 | C62: Branch 56 | D62: 345815.39 | E62: =IF(D$83=0,"n.a.",D62/D$83) -> 0.00099146407 | F62: 317819.91 | G62: =IF(F$83=0,"n.a.",F62/F$83) -> 0.00096611493 | H62: 282053.34 | I62: =IF(H$83=0,"n.a.",H62/H$83) -> 0.00083639876 | J62: 355506.42 | K62: =IF(J$83=0,"n.a.",J62/J$83) -> 0.0010392083 | L62: 368902.21 | M62: =IF(L$83=0,"n.a.",L62/L$83) -> 0.0010537013 | N62: 364710.29 | O62: =IF(N$83=0,"n.a.",N62/N$83) -> 0.0010482419 | P62: 410064.29 | Q62: =IF(P$83=0,"n.a.",P62/P$83) -> 0.0011070101 | R62: 431058.72 | S62: =IF(R$83=0,"n.a.",R62/R$83) -> 0.0011355315 | T62: 422210.89 | U62: =IF(T$83=0,"n.a.",T62/T$83) -> 0.0011647568 | V62: 476712.77 | W62: =IF(V$83=0,"n.a.",V62/V$83) -> 0.0012704524 | X62: 439823.53 | Y62: =IF(X$83=0,"n.a.",X62/X$83) -> 0.001193405 | Z62: 508758.05 | AA62: =IF(Z$83=0,"n.a.",Z62/Z$83) -> 0.0011715837 | AB62: =SUM(D62,F62,H62,J62,L62,N62,P62,R62,T62,V62,X62,Z62) -> 4723435.8 | AC62: =IF($AB$83=0,"n.a.",AB62/$AB$83) -> 0.0010869341
B63: =COUNTIFS($AB$7:$AB$75,">"&AB63)+1 -> 57 | C63: Branch 57 | Z63: 4617373.5 | AA63: =IF(Z$83=0,"n.a.",Z63/Z$83) -> 0.01063303 | AB63: =SUM(D63,F63,H63,J63,L63,N63,P63,R63,T63,V63,X63,Z63) -> 4617373.5 | AC63: =IF($AB$83=0,"n.a.",AB63/$AB$83) -> 0.0010625275
B64: =COUNTIFS($AB$7:$AB$75,">"&AB64)+1 -> 58 | C64: Branch 58 | D64: 344312 | E64: =IF(D$83=0,"n.a.",D64/D$83) -> 0.0009871538 | F64: 286552.73 | G64: =IF(F$83=0,"n.a.",F64/F$83) -> 0.00087106837 | H64: 288721.52 | I64: =IF(H$83=0,"n.a.",H64/H$83) -> 0.00085617253 | J64: 275432.7 | K64: =IF(J$83=0,"n.a.",J64/J$83) -> 0.00080513865 | L64: 334713.64 | M64: =IF(L$83=0,"n.a.",L64/L$83) -> 0.00095604798 | N64: 327824.99 | O64: =IF(N$83=0,"n.a.",N64/N$83) -> 0.00094222702 | P64: 360178.83 | Q64: =IF(P$83=0,"n.a.",P64/P$83) -> 0.00097233926 | R64: 350728.85 | S64: =IF(R$83=0,"n.a.",R64/R$83) -> 0.00092391977 | T64: 331750.22 | U64: =IF(T$83=0,"n.a.",T64/T$83) -> 0.0009152022 | V64: 352033.94 | W64: =IF(V$83=0,"n.a.",V64/V$83) -> 0.00093817993 | X64: 325046.76 | Y64: =IF(X$83=0,"n.a.",X64/X$83) -> 0.00088197286 | Z64: 322537.31 | AA64: =IF(Z$83=0,"n.a.",Z64/Z$83) -> 0.00074274887 | AB64: =SUM(D64,F64,H64,J64,L64,N64,P64,R64,T64,V64,X64,Z64) -> 3899833.5 | AC64: =IF($AB$83=0,"n.a.",AB64/$AB$83) -> 0.0008974107
B65: =COUNTIFS($AB$7:$AB$75,">"&AB65)+1 -> 59 | C65: Branch 59 | D65: 268848.84 | E65: =IF(D$83=0,"n.a.",D65/D$83) -> 0.00077079844 | F65: 219067.74 | G65: =IF(F$83=0,"n.a.",F65/F$83) -> 0.00066592623 | H65: 261451.45 | I65: =IF(H$83=0,"n.a.",H65/H$83) -> 0.00077530608 | J65: 266770.71 | K65: =IF(J$83=0,"n.a.",J65/J$83) -> 0.00077981812 | L65: 262920.19 | M65: =IF(L$83=0,"n.a.",L65/L$83) -> 0.00075098319 | N65: 275427.39 | O65: =IF(N$83=0,"n.a.",N65/N$83) -> 0.00079162705 | P65: 290835.02 | Q65: =IF(P$83=0,"n.a.",P65/P$83) -> 0.00078513862 | R65: 485263.92 | S65: =IF(R$83=0,"n.a.",R65/R$83) -> 0.0012783235 | T65: 307292.23 | U65: =IF(T$83=0,"n.a.",T65/T$83) -> 0.00084772973 | V65: 296568.35 | W65: =IF(V$83=0,"n.a.",V65/V$83) -> 0.00079036264 | X65: 333571.27 | Y65: =IF(X$83=0,"n.a.",X65/X$83) -> 0.00090510303 | Z65: 399971.05 | AA65: =IF(Z$83=0,"n.a.",Z65/Z$83) -> 0.00092106568 | AB65: =SUM(D65,F65,H65,J65,L65,N65,P65,R65,T65,V65,X65,Z65) -> 3667988.2 | AC65: =IF($AB$83=0,"n.a.",AB65/$AB$83) -> 0.00084405958
B66: =COUNTIFS($AB$7:$AB$75,">"&AB66)+1 -> 60 | C66: Branch 60 | D66: 309518.82 | E66: =IF(D$83=0,"n.a.",D66/D$83) -> 0.00088740061 | F66: 299814.49 | G66: =IF(F$83=0,"n.a.",F66/F$83) -> 0.00091138171 | H66: 358367.38 | I66: =IF(H$83=0,"n.a.",H66/H$83) -> 0.0010626998 | J66: 372997.37 | K66: =IF(J$83=0,"n.a.",J66/J$83) -> 0.0010903375 | L66: 351959.06 | M66: =IF(L$83=0,"n.a.",L66/L$83) -> 0.0010053063 | N66: 376858.99 | O66: =IF(N$83=0,"n.a.",N66/N$83) -> 0.0010831594 | P66: 333149.75 | Q66: =IF(P$83=0,"n.a.",P66/P$83) -> 0.00089937152 | R66: 373620.36 | S66: =IF(R$83=0,"n.a.",R66/R$83) -> 0.00098422253 | T66: 347776.78 | U66: =IF(T$83=0,"n.a.",T66/T$83) -> 0.00095941481 | V66: 129071.32 | W66: =IF(V$83=0,"n.a.",V66/V$83) -> 0.00034397854 | AB66: =SUM(D66,F66,H66,J66,L66,N66,P66,R66,T66,V66,X66,Z66) -> 3253134.3 | AC66: =IF($AB$83=0,"n.a.",AB66/$AB$83) -> 0.00074859544
B67: =COUNTIFS($AB$7:$AB$75,">"&AB67)+1 -> 61 | C67: Branch 61 | D67: 208119 | E67: =IF(D$83=0,"n.a.",D67/D$83) -> 0.000596684 | F67: 175439.59 | G67: =IF(F$83=0,"n.a.",F67/F$83) -> 0.00053330456 | H67: 172128.6 | I67: =IF(H$83=0,"n.a.",H67/H$83) -> 0.0005104288 | J67: 170658 | K67: =IF(J$83=0,"n.a.",J67/J$83) -> 0.00049886362 | L67: 198792.45 | M67: =IF(L$83=0,"n.a.",L67/L$83) -> 0.00056781409 | N67: 193284.53 | O67: =IF(N$83=0,"n.a.",N67/N$83) -> 0.00055553393 | P67: 190950.93 | Q67: =IF(P$83=0,"n.a.",P67/P$83) -> 0.00051549139 | R67: 201305.61 | S67: =IF(R$83=0,"n.a.",R67/R$83) -> 0.00053029636 | T67: 207390.96 | U67: =IF(T$83=0,"n.a.",T67/T$83) -> 0.00057213124 | V67: 203397.64 | W67: =IF(V$83=0,"n.a.",V67/V$83) -> 0.00054206019 | X67: 205447.19 | Y67: =IF(X$83=0,"n.a.",X67/X$83) -> 0.00055745471 | Z67: 206483.45 | AA67: =IF(Z$83=0,"n.a.",Z67/Z$83) -> 0.00047549646 | AB67: =SUM(D67,F67,H67,J67,L67,N67,P67,R67,T67,V67,X67,Z67) -> 2333398 | AC67: =IF($AB$83=0,"n.a.",AB67/$AB$83) -> 0.00053695018
B68: =COUNTIFS($AB$7:$AB$75,">"&AB68)+1 -> 62 | C68: Branch 62 | Z68: 1147415.7 | AA68: =IF(Z$83=0,"n.a.",Z68/Z$83) -> 0.0026423044 | AB68: =SUM(D68,F68,H68,J68,L68,N68,P68,R68,T68,V68,X68,Z68) -> 1147415.7 | AC68: =IF($AB$83=0,"n.a.",AB68/$AB$83) -> 0.00026403773
B69: =COUNTIFS($AB$7:$AB$75,">"&AB69)+1 -> 63 | C69: Branch 63 | Z69: 956735.77 | AA69: =IF(Z$83=0,"n.a.",Z69/Z$83) -> 0.0022032007 | AB69: =SUM(D69,F69,H69,J69,L69,N69,P69,R69,T69,V69,X69,Z69) -> 956735.77 | AC69: =IF($AB$83=0,"n.a.",AB69/$AB$83) -> 0.00022015938
B70: =COUNTIFS($AB$7:$AB$75,">"&AB70)+1 -> 64 | C70: Branch 64 | Z70: 953701.35 | AA70: =IF(Z$83=0,"n.a.",Z70/Z$83) -> 0.0021962129 | AB70: =SUM(D70,F70,H70,J70,L70,N70,P70,R70,T70,V70,X70,Z70) -> 953701.35 | AC70: =IF($AB$83=0,"n.a.",AB70/$AB$83) -> 0.00021946111
B71: =COUNTIFS($AB$7:$AB$75,">"&AB71)+1 -> 65 | C71: Branch 65 | Z71: 903702.93 | AA71: =IF(Z$83=0,"n.a.",Z71/Z$83) -> 0.002081075 | AB71: =SUM(D71,F71,H71,J71,L71,N71,P71,R71,T71,V71,X71,Z71) -> 903702.93 | AC71: =IF($AB$83=0,"n.a.",AB71/$AB$83) -> 0.00020795572
B72: =COUNTIFS($AB$7:$AB$75,">"&AB72)+1 -> 66 | C72: Branch 66 | X72: 171927.65 | Y72: =IF(X$83=0,"n.a.",X72/X$83) -> 0.00046650372 | Z72: 234849.37 | AA72: =IF(Z$83=0,"n.a.",Z72/Z$83) -> 0.00054081838 | AB72: =SUM(D72,F72,H72,J72,L72,N72,P72,R72,T72,V72,X72,Z72) -> 406777.02 | AC72: =IF($AB$83=0,"n.a.",AB72/$AB$83) -> 9.3605548e-05
B73: =COUNTIFS($AB$7:$AB$75,">"&AB73)+1 -> 67 | C73: Branch 67 | D73: 21802.03 | E73: =IF(D$83=0,"n.a.",D73/D$83) -> 6.2507135e-05 | F73: 17720.34 | G73: =IF(F$83=0,"n.a.",F73/F$83) -> 5.3866622e-05 | H73: 22739.69 | I73: =IF(H$83=0,"n.a.",H73/H$83) -> 6.7432098e-05 | J73: 18798 | K73: =IF(J$83=0,"n.a.",J73/J$83) -> 5.4949889e-05 | L73: 25668.59 | M73: =IF(L$83=0,"n.a.",L73/L$83) -> 7.3317608e-05 | N73: 21225.42 | O73: =IF(N$83=0,"n.a.",N73/N$83) -> 6.1005612e-05 | P73: 30085.62 | Q73: =IF(P$83=0,"n.a.",P73/P$83) -> 8.1219181e-05 | R73: 29253.66 | S73: =IF(R$83=0,"n.a.",R73/R$83) -> 7.706248e-05 | T73: 41534.04 | U73: =IF(T$83=0,"n.a.",T73/T$83) -> 0.00011458032 | V73: 26804.55 | W73: =IF(V$83=0,"n.a.",V73/V$83) -> 7.1434848e-05 | X73: 23119.2 | Y73: =IF(X$83=0,"n.a.",X73/X$83) -> 6.2730996e-05 | Z73: 31298.03 | AA73: =IF(Z$83=0,"n.a.",Z73/Z$83) -> 7.207407e-05 | AB73: =SUM(D73,F73,H73,J73,L73,N73,P73,R73,T73,V73,X73,Z73) -> 310049.17 | AC73: =IF($AB$83=0,"n.a.",AB73/$AB$83) -> 7.1347006e-05
B74: =COUNTIFS($AB$7:$AB$75,">"&AB74)+1 -> 68 | C74: Branch 68 | D74: 105606.91 | E74: =IF(D$83=0,"n.a.",D74/D$83) -> 0.00030277848 | F74: 68618.55 | G74: =IF(F$83=0,"n.a.",F74/F$83) -> 0.00020858796 | H74: 72435.76 | I74: =IF(H$83=0,"n.a.",H74/H$83) -> 0.00021480043 | J74: 60957.87 | K74: =IF(J$83=0,"n.a.",J74/J$83) -> 0.00017819067 | AB74: =SUM(D74,F74,H74,J74,L74,N74,P74,R74,T74,V74,X74,Z74) -> 307619.09 | AC74: =IF($AB$83=0,"n.a.",AB74/$AB$83) -> 7.0787808e-05
B75: =COUNTIFS($AB$7:$AB$75,">"&AB75)+1 -> 69 | C75: Branch 69 | L75: 0 | M75: =IF(L$83=0,"n.a.",L75/L$83) -> 0 | N75: 0 | O75: =IF(N$83=0,"n.a.",N75/N$83) -> 0 | AB75: =SUM(D75,F75,H75,J75,L75,N75,P75,R75,T75,V75,X75,Z75) -> 0 | AC75: =IF($AB$83=0,"n.a.",AB75/$AB$83) -> 0
C76: All branches | D76: =SUM(D7:D75) -> 3.436618e+08 | E76: =IF(D$83=0,"n.a.",D76/D$83) -> 0.98528965 | F76: =SUM(F7:F75) -> 3.2446936e+08 | G76: =IF(F$83=0,"n.a.",F76/F$83) -> 0.98632806 | H76: =SUM(H7:H75) -> 3.3113887e+08 | I76: =IF(H$83=0,"n.a.",H76/H$83) -> 0.98195661 | J76: =SUM(J7:J75) -> 3.3796005e+08 | K76: =IF(J$83=0,"n.a.",J76/J$83) -> 0.98791718 | L76: =SUM(L7:L75) -> 3.4616818e+08 | M76: =IF(L$83=0,"n.a.",L76/L$83) -> 0.98876575 | N76: =SUM(N7:N75) -> 3.4415078e+08 | O76: =IF(N$83=0,"n.a.",N76/N$83) -> 0.98915024 | P76: =SUM(P7:P75) -> 3.66446e+08 | Q76: =IF(P$83=0,"n.a.",P76/P$83) -> 0.98925812 | R76: =SUM(R7:R75) -> 3.7652954e+08 | S76: =IF(R$83=0,"n.a.",R76/R$83) -> 0.99188614 | T76: =SUM(T7:T75) -> 3.5489076e+08 | U76: =IF(T$83=0,"n.a.",T76/T$83) -> 0.97904021 | V76: =SUM(V7:V75) -> 3.6901342e+08 | W76: =IF(V$83=0,"n.a.",V76/V$83) -> 0.98343071 | X76: =SUM(X7:X75) -> 3.6223475e+08 | Y76: =IF(X$83=0,"n.a.",X76/X$83) -> 0.98287773 | Z76: =SUM(Z7:Z75) -> 4.26991e+08 | AA76: =IF(Z$83=0,"n.a.",Z76/Z$83) -> 0.98328807 | AB76: =SUM(AB7:AB75) -> 4.2836545e+09 | AC76: =IF($AB$83=0,"n.a.",AB76/$AB$83) -> 0.98573373
C78: Other reported units (excluded from branch ranking)
C79: Special orders | D79: 5130863 | E79: =IF(D$83=0,"n.a.",D79/D$83) -> 0.014710353 | F79: 4497617 | G79: =IF(F$83=0,"n.a.",F79/F$83) -> 0.013671941 | H79: 6084655.9 | I79: =IF(H$83=0,"n.a.",H79/H$83) -> 0.018043391 | J79: 4133454.3 | K79: =IF(J$83=0,"n.a.",J79/J$83) -> 0.01208282 | L79: 3933125.3 | M79: =IF(L$83=0,"n.a.",L79/L$83) -> 0.011234249 | N79: 3774911.3 | O79: =IF(N$83=0,"n.a.",N79/N$83) -> 0.010849763 | P79: 3979061.9 | Q79: =IF(P$83=0,"n.a.",P79/P$83) -> 0.010741881 | R79: 3080099.9 | S79: =IF(R$83=0,"n.a.",R79/R$83) -> 0.0081138611 | T79: 7597680.5 | U79: =IF(T$83=0,"n.a.",T79/T$83) -> 0.020959787 | V79: 6217308.3 | W79: =IF(V$83=0,"n.a.",V79/V$83) -> 0.016569294 | X79: 6310329.1 | Y79: =IF(X$83=0,"n.a.",X79/X$83) -> 0.017122272 | Z79: 7257125.7 | AA79: =IF(Z$83=0,"n.a.",Z79/Z$83) -> 0.016711933 | AB79: =SUM(D79,F79,H79,J79,L79,N79,P79,R79,T79,V79,X79,Z79) -> 61996232 | AC79: =IF($AB$83=0,"n.a.",AB79/$AB$83) -> 0.014266271
C80: Central production | V80: 0 | W80: =IF(V$83=0,"n.a.",V80/V$83) -> 0 | AB80: =SUM(D80,F80,H80,J80,L80,N80,P80,R80,T80,V80,X80,Z80) -> 0 | AC80: =IF($AB$83=0,"n.a.",AB80/$AB$83) -> 0
C81: Head office | P81: 0 | Q81: =IF(P$83=0,"n.a.",P81/P$83) -> 0 | AB81: =SUM(D81,F81,H81,J81,L81,N81,P81,R81,T81,V81,X81,Z81) -> 0 | AC81: =IF($AB$83=0,"n.a.",AB81/$AB$83) -> 0
C83: Company total | D83: =SUM(D76,D79:D81) -> 3.4879266e+08 | E83: =IF(D$83=0,"n.a.",D83/D$83) -> 1 | F83: =SUM(F76,F79:F81) -> 3.2896698e+08 | G83: =IF(F$83=0,"n.a.",F83/F$83) -> 1 | H83: =SUM(H76,H79:H81) -> 3.3722353e+08 | I83: =IF(H$83=0,"n.a.",H83/H$83) -> 1 | J83: =SUM(J76,J79:J81) -> 3.420935e+08 | K83: =IF(J$83=0,"n.a.",J83/J$83) -> 1 | L83: =SUM(L76,L79:L81) -> 3.501013e+08 | M83: =IF(L$83=0,"n.a.",L83/L$83) -> 1 | N83: =SUM(N76,N79:N81) -> 3.4792569e+08 | O83: =IF(N$83=0,"n.a.",N83/N$83) -> 1 | P83: =SUM(P76,P79:P81) -> 3.7042506e+08 | Q83: =IF(P$83=0,"n.a.",P83/P$83) -> 1 | R83: =SUM(R76,R79:R81) -> 3.7960964e+08 | S83: =IF(R$83=0,"n.a.",R83/R$83) -> 1 | T83: =SUM(T76,T79:T81) -> 3.6248844e+08 | U83: =IF(T$83=0,"n.a.",T83/T$83) -> 1 | V83: =SUM(V76,V79:V81) -> 3.7523073e+08 | W83: =IF(V$83=0,"n.a.",V83/V$83) -> 1 | X83: =SUM(X76,X79:X81) -> 3.6854508e+08 | Y83: =IF(X$83=0,"n.a.",X83/X$83) -> 1 | Z83: =SUM(Z76,Z79:Z81) -> 4.3424813e+08 | AA83: =IF(Z$83=0,"n.a.",Z83/Z$83) -> 1 | AB83: =SUM(AB76,AB79:AB81) -> 4.3456507e+09 | AC83: =IF($AB$83=0,"n.a.",AB83/$AB$83) -> 1
C87: Report total | D87: 3.4879266e+08 | F87: 3.2896698e+08 | H87: 3.3722353e+08 | J87: 3.420935e+08 | L87: 3.501013e+08 | N87: 3.4792569e+08 | P87: 3.7042506e+08 | R87: 3.7960964e+08 | T87: 3.6248844e+08 | V87: 3.7523073e+08 | X87: 3.6854508e+08 | Z87: 4.3424813e+08 | AB87: 4.3456507e+09
C88: Difference | D88: =ROUND(D83-D87,2) -> 0 | F88: =ROUND(F83-F87,2) -> 0 | H88: =ROUND(H83-H87,2) -> 0 | J88: =ROUND(J83-J87,2) -> 0 | L88: =ROUND(L83-L87,2) -> 0 | N88: =ROUND(N83-N87,2) -> 0 | P88: =ROUND(P83-P87,2) -> 0 | R88: =ROUND(R83-R87,2) -> 0 | T88: =ROUND(T83-T87,2) -> 0 | V88: =ROUND(V83-V87,2) -> 0 | X88: =ROUND(X83-X87,2) -> 0 | Z88: =ROUND(Z83-Z87,2) -> 0 | AB88: =ROUND(AB83-AB87,2) -> 0
C90: Detailed 2025 P&L revenue converted from KSh thousands to KSh | AB90: =SUM('Profit and Loss'!G6:G8)*1000 -> 4345650744
C91: Sales report less detailed P&L revenue (KSh) | AB91: =ROUND(AB83-AB90,2) -> -0.64
C92: The small difference to the detailed P&L is retained. Source figures have not been adjusted to force agreement.
C93: Rows are sorted by the supplied 2025 totals. After editing amounts, re-sort Total sales 2025 from largest to smallest.

Sheet Monthly Sales Ranking
C2: Demo Café Group
C3: Monthly sales ranking
B5: Rank | C5: Month | D5: Sales (KSh) | E5: % of annual sales | F5: Month-on-month % | G5: Remarks
B6: =COUNTIFS($D$6:$D$17,">"&D6)+1 -> 1 | C6: December | D6: ='Branch Sales'!Z83 -> 4.3424813e+08 | E6: =IF($D$18=0,"n.a.",D6/$D$18) -> 0.099927066 | F6: =IF(D10=0,"n.a.",D6/D10-1) -> 0.17827683 | G6: December sales were KSh 434.248m, representing 10.0% of annual sales. This was an increase of 17.8% from the previous month. Festive-season trading and five additional branches with positive sales supported the increase. Existing branches and other channels contributed most of the month-on-month growth.
B7: =COUNTIFS($D$6:$D$17,">"&D7)+1 -> 2 | C7: August | D7: ='Branch Sales'!R83 -> 3.7960964e+08 | E7: =IF($D$18=0,"n.a.",D7/$D$18) -> 0.087353922 | F7: =IF(D9=0,"n.a.",D7/D9-1) -> 0.0247947 | G7: August sales were KSh 379.610m, representing 8.7% of annual sales. This was an increase of 2.5% from the previous month. School-holiday and tourism demand supported sales, following the increase recorded in July. The month remained one of the strongest trading periods of the year.
B8: =COUNTIFS($D$6:$D$17,">"&D8)+1 -> 3 | C8: October | D8: ='Branch Sales'!V83 -> 3.7523073e+08 | E8: =IF($D$18=0,"n.a.",D8/$D$18) -> 0.086346269 | F8: =IF(D11=0,"n.a.",D8/D11-1) -> 0.03515226 | G8: October sales were KSh 375.231m, representing 8.6% of annual sales. This was an increase of 3.5% from the previous month. Sales recovered from the September decline and returned close to the August peak. The improvement was broad enough to lift October to the third-highest month.
B9: =COUNTIFS($D$6:$D$17,">"&D9)+1 -> 4 | C9: July | D9: ='Branch Sales'!P83 -> 3.7042506e+08 | E9: =IF($D$18=0,"n.a.",D9/$D$18) -> 0.085240412 | F9: =IF(D14=0,"n.a.",D9/D14-1) -> 0.064667156 | G9: July sales were KSh 370.425m, representing 8.5% of annual sales. This was an increase of 6.5% from the previous month. The increase is consistent with school-holiday and tourism demand. Sales moved above the first-half monthly range and remained elevated through August.
B10: =COUNTIFS($D$6:$D$17,">"&D10)+1 -> 5 | C10: November | D10: ='Branch Sales'!X83 -> 3.6854508e+08 | E10: =IF($D$18=0,"n.a.",D10/$D$18) -> 0.084807801 | F10: =IF(D8=0,"n.a.",D10/D8-1) -> -0.017817431 | G10: November sales were KSh 368.545m, representing 8.5% of annual sales. This was a decrease of 1.8% from the previous month. Sales eased slightly after October but remained above most first-half months. The decline appears to be normal monthly variation ahead of the December peak.
B11: =COUNTIFS($D$6:$D$17,">"&D11)+1 -> 6 | C11: September | D11: ='Branch Sales'!T83 -> 3.6248844e+08 | E11: =IF($D$18=0,"n.a.",D11/$D$18) -> 0.083414076 | F11: =IF(D7=0,"n.a.",D11/D7-1) -> -0.045102114 | G11: September sales were KSh 362.488m, representing 8.3% of annual sales. This was a decrease of 4.5% from the previous month. Sales reduced after the August peak, consistent with normalisation after the school-holiday period. Despite the fall, September remained above the first-half monthly average.
B12: =COUNTIFS($D$6:$D$17,">"&D12)+1 -> 7 | C12: May | D12: ='Branch Sales'!L83 -> 3.501013e+08 | E12: =IF($D$18=0,"n.a.",D12/$D$18) -> 0.080563608 | F12: =IF(D15=0,"n.a.",D12/D15-1) -> 0.023408224 | G12: May sales were KSh 350.101m, representing 8.1% of annual sales. This was an increase of 2.3% from the previous month. The increase followed the modest improvement in April and reflects continued trading across the expanded network. Sales remained close to the annual monthly average.
B13: =COUNTIFS($D$6:$D$17,">"&D13)+1 -> 8 | C13: January | D13: ='Branch Sales'!D83 -> 3.4879266e+08 | E13: =IF($D$18=0,"n.a.",D13/$D$18) -> 0.080262469 | G13: January sales were KSh 348.793m, representing 8.0% of annual sales. January provides the opening monthly base for the year, so no month-on-month percentage is shown. Sales represented 8.0% of the annual total.
B14: =COUNTIFS($D$6:$D$17,">"&D14)+1 -> 9 | C14: June | D14: ='Branch Sales'!N83 -> 3.4792569e+08 | E14: =IF($D$18=0,"n.a.",D14/$D$18) -> 0.080062968 | F14: =IF(D12=0,"n.a.",D14/D12-1) -> -0.0062142182 | G14: June sales were KSh 347.926m, representing 8.0% of annual sales. This was a decrease of 0.6% from the previous month. Sales were broadly stable compared with May, with only a 0.6% decrease. The limited movement indicates a steady trading run rate before the July increase.
B15: =COUNTIFS($D$6:$D$17,">"&D15)+1 -> 10 | C15: April | D15: ='Branch Sales'!J83 -> 3.420935e+08 | E15: =IF($D$18=0,"n.a.",D15/$D$18) -> 0.078720891 | F15: =IF(D16=0,"n.a.",D15/D16-1) -> 0.014441377 | G15: April sales were KSh 342.093m, representing 7.9% of annual sales. This was an increase of 1.4% from the previous month. Sales increased modestly from March despite April having one fewer calendar day. This indicates an improvement in the average daily sales rate.
B16: =COUNTIFS($D$6:$D$17,">"&D16)+1 -> 11 | C16: March | D16: ='Branch Sales'!H83 -> 3.3722353e+08 | E16: =IF($D$18=0,"n.a.",D16/$D$18) -> 0.077600237 | F16: =IF(D17=0,"n.a.",D16/D17-1) -> 0.025098408 | G16: March sales were KSh 337.224m, representing 7.8% of annual sales. This was an increase of 2.5% from the previous month. March benefited from three more trading days than February. The monthly total rose even though the implied daily run rate was lower than in February.
B17: =COUNTIFS($D$6:$D$17,">"&D17)+1 -> 12 | C17: February | D17: ='Branch Sales'!F83 -> 3.2896698e+08 | E17: =IF($D$18=0,"n.a.",D17/$D$18) -> 0.07570028 | F17: =IF(D13=0,"n.a.",D17/D13-1) -> -0.056840875 | G17: February sales were KSh 328.967m, representing 7.6% of annual sales. This was a decrease of 5.7% from the previous month. The decline mainly reflects February having 28 days compared with 31 in January. On a daily basis, sales were stronger, so the lower monthly total was calendar-driven.
C18: Full year | D18: =SUM(D6:D17) -> 4.3456507e+09 | E18: =SUM(E6:E17) -> 1
